Workbook

Sheet Checklist
A1: Agent training checklist (HHCS CareDesk)
A2: A module is complete only when each agent has attended it and passed its competency check on the Record sheet. Scripts existing is not completion.
A4: # | B4: Module | C4: Content and source | D4: Competency check | E4: Prerequisite | F4: Agents trained | G4: Agents passed | H4: Module status
A5: 1 | B5: Login, roles and data protection | C5: TOTP sign-in, idle sign-out, masked numbers, what agents may not see (costs, recordings beyond own). DPDP: no patient details in notes outside the case. | D5: Supervisor observes sign-in; 3-question check on what may not be shared. | E5: Login created | F5: =COUNTIFS(Record!$D$7:$D$500,B5,Record!$F$7:$F$500,"Yes") -> 0 | G5: =COUNTIFS(Record!$D$7:$D$500,B5,Record!$K$7:$K$500,"Pass") -> 0 | H5: =IF(COUNTA(Roster!$A$7:$A$500)=0,"Not started",IF(G5>=COUNTA(Roster!$A$7:$A$500),"Complete","In progress")) -> Not started
A6: 2 | B6: Inbound opening and consent (S-01) | C6: S-01 including the recording consent and the S-09 hand-off. | D6: Role-play: consent asked and a clear yes recorded; emergency cue routed to S-09. | E6: Script approver recorded | F6: =COUNTIFS(Record!$D$7:$D$500,B6,Record!$F$7:$F$500,"Yes") -> 0 | G6: =COUNTIFS(Record!$D$7:$D$500,B6,Record!$K$7:$K$500,"Pass") -> 0 | H6: =IF(COUNTA(Roster!$A$7:$A$500)=0,"Not started",IF(G6>=COUNTA(Roster!$A$7:$A$500),"Complete","In progress")) -> Not started
A7: 3 | B7: Emergency at home (S-09) | C7: S-09; one-click emergency escalation. | D7: Role-play with chest-pain cue: 108 advised, escalation raised, no clinical advice. | E7: Hinduja clinical sign-off | F7: =COUNTIFS(Record!$D$7:$D$500,B7,Record!$F$7:$F$500,"Yes") -> 0 | G7: =COUNTIFS(Record!$D$7:$D$500,B7,Record!$K$7:$K$500,"Pass") -> 0 | H7: =IF(COUNTA(Roster!$A$7:$A$500)=0,"Not started",IF(G7>=COUNTA(Roster!$A$7:$A$500),"Complete","In progress")) -> Not started
A8: 4 | B8: Requirement capture (S-04) and enquiry form | C8: S-04; Agent console enquiry fields: discharge date, service start, preferred slot, nursing day / night shift, referral source. | D8: Observed live or recorded call: all S-04 fields captured and read back. | E8: None | F8: =COUNTIFS(Record!$D$7:$D$500,B8,Record!$F$7:$F$500,"Yes") -> 0 | G8: =COUNTIFS(Record!$D$7:$D$500,B8,Record!$K$7:$K$500,"Pass") -> 0 | H8: =IF(COUNTA(Roster!$A$7:$A$500)=0,"Not started",IF(G8>=COUNTA(Roster!$A$7:$A$500),"Complete","In progress")) -> Not started
A9: 5 | B9: Dispositions and callback outcomes | C9: 8 intake dispositions (Knowledge page guide); callback outcomes Resolved / Follow-up needed / Wrong number / No longer needed; unreachable rules. | D9: Quiz: correct disposition for 8 scenarios; correct outcome for 4 callback scenarios. | E9: S-03 correction approved | F9: =COUNTIFS(Record!$D$7:$D$500,B9,Record!$F$7:$F$500,"Yes") -> 0 | G9: =COUNTIFS(Record!$D$7:$D$500,B9,Record!$K$7:$K$500,"Pass") -> 0 | H9: =IF(COUNTA(Roster!$A$7:$A$500)=0,"Not started",IF(G9>=COUNTA(Roster!$A$7:$A$500),"Complete","In progress")) -> Not started
A10: 6 | B10: Callbacks (S-03) and quote follow-up (S-08) | C10: S-03; Callbacks page; proposed S-08. | D10: Role-play: missed-call callback closed with the right outcome. | E10: S-03 fix and S-08 approved | F10: =COUNTIFS(Record!$D$7:$D$500,B10,Record!$F$7:$F$500,"Yes") -> 0 | G10: =COUNTIFS(Record!$D$7:$D$500,B10,Record!$K$7:$K$500,"Pass") -> 0 | H10: =IF(COUNTA(Roster!$A$7:$A$500)=0,"Not started",IF(G10>=COUNTA(Roster!$A$7:$A$500),"Complete","In progress")) -> Not started
A11: 7 | B11: Diagnostics at home (S-05) | C11: S-05; lab, ECG, X-ray rate-card items and preparation notes. | D11: Quote 3 diagnostic requests correctly from the rate card, including fasting advice. | E11: X-ray overlap decided | F11: =COUNTIFS(Record!$D$7:$D$500,B11,Record!$F$7:$F$500,"Yes") -> 0 | G11: =COUNTIFS(Record!$D$7:$D$500,B11,Record!$K$7:$K$500,"Pass") -> 0 | H11: =IF(COUNTA(Roster!$A$7:$A$500)=0,"Not started",IF(G11>=COUNTA(Roster!$A$7:$A$500),"Complete","In progress")) -> Not started
A12: 8 | B12: Pricing and budget (S-06, S-02) | C12: Itemised quote from the locked rate card, discount approval path, "quote after assessment" for unpriced items. | D12: Role-play: itemised quote; no discount promised; unpriced item handled as quote after assessment. | E12: Approved price list imported and active | F12: =COUNTIFS(Record!$D$7:$D$500,B12,Record!$F$7:$F$500,"Yes") -> 0 | G12: =COUNTIFS(Record!$D$7:$D$500,B12,Record!$K$7:$K$500,"Pass") -> 0 | H12: =IF(COUNTA(Roster!$A$7:$A$500)=0,"Not started",IF(G12>=COUNTA(Roster!$A$7:$A$500),"Complete","In progress")) -> Not started
A13: 9 | B13: Product knowledge by service | C13: Product knowledge page: summary, questions, includes / excludes, preparation, FAQs per service. | D13: Answer 10 FAQ questions from the panel without inventing content. | E13: Service notes approved and imported | F13: =COUNTIFS(Record!$D$7:$D$500,B13,Record!$F$7:$F$500,"Yes") -> 0 | G13: =COUNTIFS(Record!$D$7:$D$500,B13,Record!$K$7:$K$500,"Pass") -> 0 | H13: =IF(COUNTA(Roster!$A$7:$A$500)=0,"Not started",IF(G13>=COUNTA(Roster!$A$7:$A$500),"Complete","In progress")) -> Not started
A14: 10 | B14: Closing (S-07) | C14: S-07; case number, next steps, helpline. | D14: Observed call: summary, next steps and disposition set. | E14: None | F14: =COUNTIFS(Record!$D$7:$D$500,B14,Record!$F$7:$F$500,"Yes") -> 0 | G14: =COUNTIFS(Record!$D$7:$D$500,B14,Record!$K$7:$K$500,"Pass") -> 0 | H14: =IF(COUNTA(Roster!$A$7:$A$500)=0,"Not started",IF(G14>=COUNTA(Roster!$A$7:$A$500),"Complete","In progress")) -> Not started
A16: Module status is "Complete" only when the number of agents who passed equals the roster size. Example rows on Record and Roster are excluded (they start with EXAMPLE).
B17: Operations owner sign-off | D17: Name / date / signature

Sheet Roster
A1: Agent roster
A2: Legend: fill rows from row 7. Row 6 is an example and is not counted.
A5: Agent name | B5: Agent code | C5: Role | D5: Branch | E5: Start date | F5: Notes
A6: EXAMPLE A. Agent | B6: AG-00 | C6: agent | D6: Khar | E6: 2026-10-20 | F6: Example row, not counted

Sheet Record
A1: Attendance and competency record
A2: Legend: one row per agent per module. Yellow cells are filled by the trainer / assessor from row 7. Row 6 is an example and is not counted. Result is computed.
A3: Pass mark (%) | B3: 80 | C3: Set by the operations owner; 80 is a placeholder until agreed.
A5: Agent name | B5: Agent code | C5: Session date | D5: Module | E5: Trainer | F5: Attended | G5: Check method | H5: Score (%) | I5: Assessor | J5: Evidence (call ID / quiz file) | K5: Result | L5: Retrain by | M5: Notes
A6: EXAMPLE A. Agent | B6: AG-00 | C6: 2026-10-20 | D6: Inbound opening and consent (S-01) | E6: Trainer name | F6: Yes | G6: Role-play | H6: 85 | I6: Assessor name | J6: Call HHC-0000 | K6: EXAMPLE | M6: Example row, not counted
K7: =IF(OR(F7="",H7=""),"",IF(AND(F7="Yes",H7>=$B$3),"Pass","Not yet"))
K8: =IF(OR(F8="",H8=""),"",IF(AND(F8="Yes",H8>=$B$3),"Pass","Not yet"))
K9: =IF(OR(F9="",H9=""),"",IF(AND(F9="Yes",H9>=$B$3),"Pass","Not yet"))
K10: =IF(OR(F10="",H10=""),"",IF(AND(F10="Yes",H10>=$B$3),"Pass","Not yet"))
K11: =IF(OR(F11="",H11=""),"",IF(AND(F11="Yes",H11>=$B$3),"Pass","Not yet"))
K12: =IF(OR(F12="",H12=""),"",IF(AND(F12="Yes",H12>=$B$3),"Pass","Not yet"))
K13: =IF(OR(F13="",H13=""),"",IF(AND(F13="Yes",H13>=$B$3),"Pass","Not yet"))
K14: =IF(OR(F14="",H14=""),"",IF(AND(F14="Yes",H14>=$B$3),"Pass","Not yet"))
K15: =IF(OR(F15="",H15=""),"",IF(AND(F15="Yes",H15>=$B$3),"Pass","Not yet"))
K16: =IF(OR(F16="",H16=""),"",IF(AND(F16="Yes",H16>=$B$3),"Pass","Not yet"))
K17: =IF(OR(F17="",H17=""),"",IF(AND(F17="Yes",H17>=$B$3),"Pass","Not yet"))
K18: =IF(OR(F18="",H18=""),"",IF(AND(F18="Yes",H18>=$B$3),"Pass","Not yet"))
... K206: =IF(OR(F206="",H206=""),"",IF(AND(F206="Yes",H206>=$B$3),"Pass","Not yet"))
