Workbook

Sheet Summary
A1: HHCS CareDesk: catalogue, pricing and training readiness
A3: Status | B3: Not ready. No approved final price list was available and the live database could not be read, so no price was imported, approved or activated.
A4: What this reconciles | B4: The CRM rate card as the repo migrations define it, against the only catalogue file in the repo: a planning draft ("85 Services Catalogue", 95 rows). The draft is not an approved list.
A5: Headline counts | B5: See Totals. All counts are formulas over the Reconciliation sheet.
A6: Cost confidentiality | B6: Verified by tests and code reading: see Verification evidence. Two paths (BMM API, partner sheet) were checked by reading only.
A7: Next step | B7: Send the approved price list file (or confirm the draft line by line on "Draft values to confirm"), plus the GST basis, effective date and unit decisions. Then run Import rates > Check file and share the check report before Submit.
A8: Sheets | B8: Totals, Reconciliation, Unresolved inputs, Unit decisions, Draft values to confirm, Knowledge coverage, Scripts review, Proposed S-08, Awaiting approval, Verification evidence, Assumptions.
A9: Yellow cells | B9: For the business owner to fill. Everything else is computed or sourced.

Sheet Totals
A1: Totals
A2: Every count is a formula over the Reconciliation sheet. "Approved list" cannot be counted: no approved list was available.
A4: Measure | B4: Against the approved list | C4: CRM rate card (repo migrations) | D4: Unapproved draft (reference only) | E4: How it is counted
A5: Expected services | B5: Not determinable | C5: =COUNTIF(Reconciliation!$Y$6:$Y$110,"Y") -> 40 | D5: =COUNTIF(Reconciliation!$Z$6:$Z$110,"Y") -> 95 | E5: Rows present in each source. The 80 to 90 figure is an expectation only; the draft has 95 rows despite its "85" title.
A6: Matched (same code in CRM and draft) | B6: Not determinable | C6: =COUNTIFS(Reconciliation!$Y$6:$Y$110,"Y",Reconciliation!$Z$6:$Z$110,"Y") -> 30 | D6: =COUNTIFS(Reconciliation!$Y$6:$Y$110,"Y",Reconciliation!$Z$6:$Z$110,"Y") -> 30 | E6: Exact code only. Similar names are never matched (importer rule).
A7: Missing from the CRM | B7: Not determinable | D7: =COUNTIFS(Reconciliation!$Z$6:$Z$110,"Y",Reconciliation!$Y$6:$Y$110,"N") -> 65 | E7: In the draft, not on the rate card.
A8: On the CRM but not in the draft | B8: Not determinable | C8: =COUNTIFS(Reconciliation!$Y$6:$Y$110,"Y",Reconciliation!$Z$6:$Z$110,"N") -> 10 | E8: Mostly generic BMM codes and the three home X-ray items.
A9: Duplicate codes | B9: Not determinable | C9: =SUMPRODUCT((COUNTIF(Reconciliation!$A$6:$A$110,Reconciliation!$A$6:$A$110)>1)*(Reconciliation!$Y$6:$Y$110="Y")) -> 0 | D9: 0 | E9: Codes appearing more than once. The draft was checked separately in Python: 95 rows, 95 unique codes, no duplicate names.
A10: Possible overlaps (generic vs specific) | B10: Not determinable | C10: =COUNTIFS(Reconciliation!$AG$6:$AG$110,1,Reconciliation!$Y$6:$Y$110,"Y") -> 12 | D10: =COUNTIFS(Reconciliation!$AG$6:$AG$110,1,Reconciliation!$Z$6:$Z$110,"Y") -> 21 | E10: E.g. BED-HOSP vs BED-SEMI / BED-FOWL; XR-HOME vs XR-CHEST. A business decision, not merged automatically.
A11: Inactive | B11: Not determinable | C11: =COUNTIFS(Reconciliation!$W$6:$W$110,"Inactive",Reconciliation!$Y$6:$Y$110,"Y") -> 0 | E11: services.active = false.
A12: Awaiting approval | B12: Not determinable | C12: 0 in repo; live unknown | E12: No rate_imports and no pending approvals exist in the migration end state. Live Approvals page not readable from here.
A13: Active but not priced (Rs 0) | B13: Not determinable | C13: =COUNTIF(Reconciliation!$AH$6:$AH$110,1) -> 25 | E13: Seeded with price 0 and an automatic approved_at; not quotable.
A14: Missing buying cost | B14: Not determinable | C14: =COUNTIF(Reconciliation!$AE$6:$AE$110,1) -> 40 | E14: provider_rates has 0 rows in the migration end state.
A15: Buying cost derivable by the 70% rule now | B15: Not determinable | C15: =COUNT(Reconciliation!$P$6:$P$110) -> 15 | E15: CRM rows with a selling price above 0.
A16: Draft B2B not equal to 70% of draft B2C | B16: Not determinable | D16: =COUNTIF(Reconciliation!$Q$6:$Q$110,"Differs*") -> 94 | E16: Would be provider-specific exceptions. None is documented as approved.
A17: Unit mismatch or unit needing a decision | B17: Not determinable | C17: =COUNTIFS(Reconciliation!$AC$6:$AC$110,1,Reconciliation!$Y$6:$Y$110,"Y") -> 16 | D17: =COUNTIFS(Reconciliation!$AC$6:$AC$110,1,Reconciliation!$Z$6:$Z$110,"Y") -> 31 | E17: Different wording between sources, 24 h labelled "shift", pack size differences, free-text units.
A18: GST basis not confirmed | B18: Not determinable | C18: =COUNTIFS(Reconciliation!$AD$6:$AD$110,1,Reconciliation!$Y$6:$Y$110,"Y") -> 40 | D18: =COUNTIFS(Reconciliation!$AD$6:$AD$110,1,Reconciliation!$Z$6:$Z$110,"Y") -> 95 | E18: No row in either source states incl_gst / excl_gst / no_gst.
A19: Tax mismatch (two confirmed bases disagree) | B19: Not determinable | C19: 0 | D19: 0 | E19: Cannot occur yet: no basis is confirmed anywhere.
A20: Effective date missing | B20: Not determinable | C20: =COUNTIFS(Reconciliation!$V$6:$V$110,"Not given",Reconciliation!$Y$6:$Y$110,"Y") -> 40 | D20: =COUNTIFS(Reconciliation!$V$6:$V$110,"Not given",Reconciliation!$Z$6:$Z$110,"Y") -> 95 | E20: Neither source carries an effective date.
A21: Knowledge gaps (no service-specific notes) | B21: Not determinable | C21: =COUNTIFS(Reconciliation!$AF$6:$AF$110,1,Reconciliation!$Y$6:$Y$110,"Y") -> 40 | D21: =COUNTIFS(Reconciliation!$AF$6:$AF$110,1,Reconciliation!$Z$6:$Z$110,"Y") -> 95 | E21: service_knowledge holds 12 category defaults and 0 service rows.
A22: Name or meaning differs on a matched code | B22: Not determinable | C22: =COUNTIF(Reconciliation!$AI$6:$AI$110,1) -> 1 | E22: VISIT-STD: "Home visit charge" vs "Home Assessment & Care Coordinator Visit".

Sheet Assumptions
A1: Assumptions
A3: Item | B3: Value | C3: Source
A4: B2B as a share of B2C (HHCS rule) | B4: 0.7 | C4: docs/RATES-AND-MARGINS.md, "B2B = % of B2C": HHCS rule (Oct 2026) 70; commit 3af8698. Used only for the derivation column; the importer computes the real value on the server.
A5: Provider by category | B5: SM / BMM | C5: docs/RATES-AND-MARGINS.md: lab, X-ray, ECG and visit to SecondMedic; everything else (incl. "other") to Book My Medicare.
A6: Unit comparison | B6: normalised | C6: Trimmed, lower-cased, leading "per" dropped. Never converted (docs/RATES-AND-MARGINS.md, Terms > Unit).

Sheet Reconciliation
A1: Service reconciliation: CRM rate card vs the only catalogue file found (unapproved draft)
A2: No approved final price list was available, and the live database could not be read. "Approved B2C" is therefore blank on every row. CRM values are the end state of all repo migrations applied to a throwaway database; the live database may differ if imports or approvals were done in the app.
A5: Code | B5: CRM name | C5: Draft name | D5: Category | E5: Delivery provider (routing) | F5: Draft provider | G5: CRM unit | H5: Draft unit | I5: Unit note | J5: CRM B2C (Rs) | K5: Draft B2C (Rs, unapproved) | L5: Approved B2C (Rs) | M5: B2C status | N5: CRM B2B | O5: Draft B2B (Rs, unapproved) | P5: 70% of CRM B2C (Rs, derivation) | Q5: Draft B2B vs 70% of draft B2C | R5: B2B status | S5: CRM GST basis | T5: Draft GST | U5: Tax status | V5: Effective date | W5: Approval / activation | X5: Knowledge coverage | Y5: On CRM rate card | Z5: In draft | AA5: Possible overlap with | AB5: Issues | AC5: Flag: unit | AD5: Flag: GST basis | AE5: Flag: no B2B | AF5: Flag: knowledge | AG5: Flag: overlap | AH5: Flag: unpriced | AI5: Flag: meaning differs
A6: BED-FOWL | C6: Full Fowler 2-Function Hospital Bed (Rental) | D6: beds | E6: Book My Medicare (BMM) | F6: Book My Medicare (BMM) | H6: day | I6: Daily rental. No monthly rental rate exists in any source; a month is not 30 day rates. | K6: 240 | M6: Not on the CRM rate card | N6: Not loaded | O6: 160 | P6: =IF(AND(ISNUMBER(J6),J6>0),ROUND(J6*Assumptions!$B$4,2),"") | Q6: =IF(AND(ISNUMBER(K6),ISNUMBER(O6)),IF(ROUND(K6*Assumptions!$B$4,2)=O6,"Equals 70%","Differs ("&TEXT(O6/K6,"0%")&" of B2C)"),"") -> Differs (67% of B2C) | R6: Not loaded. Draft B2B is unapproved. | T6: 18% GST | U6: Not confirmed: CRM basis is empty; draft gives a GST rate, not whether prices include it | V6: Not given | W6: Not loaded | X6: No service yet. Category notes (beds) would apply after import. | Y6: N | Z6: Y | AA6: BED-HOSP | AB6: GST basis, Knowledge, Possible overlap | AC6: 0 | AD6: 1 | AE6: 0 | AF6: 1 | AG6: 1 | AH6: 0 | AI6: 0
A7: BED-HOSP | B7: Hospital bed on rent | D7: beds | E7: Book My Medicare (BMM) | G7: day | I7: Daily rental. No monthly rental rate exists in any source; a month is not 30 day rates. | J7: 0 | M7: Not priced: Rs 0 placeholder, agents see "quote required" | N7: None (0 buying rates in CRM) | P7: =IF(AND(ISNUMBER(J7),J7>0),ROUND(J7*Assumptions!$B$4,2),"") | Q7: =IF(AND(ISNUMBER(K7),ISNUMBER(O7)),IF(ROUND(K7*Assumptions!$B$4,2)=O7,"Equals 70%","Differs ("&TEXT(O7/K7,"0%")&" of B2C)"),"") | R7: No buying rate, and none derivable: no selling price. | S7: Not set | U7: Not confirmed: CRM basis is empty | V7: Not given | W7: Active, not quotable (Rs 0) | X7: Category notes only (beds). No service-specific notes. | Y7: Y | Z7: N | AA7: BED-SEMI, BED-FOWL | AB7: Unpriced, No B2B, GST basis, Knowledge, Possible overlap | AC7: 0 | AD7: 1 | AE7: 1 | AF7: 1 | AG7: 1 | AH7: 1 | AI7: 0
A8: BED-ICU | B8: ICU bed (motorised), rental | C8: Motorized ICU Bed (3/5 Function with Remote) | D8: beds | E8: Book My Medicare (BMM) | F8: Book My Medicare (BMM) | G8: day | H8: day | I8: Daily rental. No monthly rental rate exists in any source; a month is not 30 day rates. | J8: 0 | K8: 450 | M8: Not priced: Rs 0 placeholder, agents see "quote required" | N8: None (0 buying rates in CRM) | O8: 300 | P8: =IF(AND(ISNUMBER(J8),J8>0),ROUND(J8*Assumptions!$B$4,2),"") | Q8: =IF(AND(ISNUMBER(K8),ISNUMBER(O8)),IF(ROUND(K8*Assumptions!$B$4,2)=O8,"Equals 70%","Differs ("&TEXT(O8/K8,"0%")&" of B2C)"),"") -> Differs (67% of B2C) | R8: No buying rate, and none derivable: no selling price. Draft B2B is unapproved. | S8: Not set | T8: 18% GST | U8: Not confirmed: CRM basis is empty; draft gives a GST rate, not whether prices include it | V8: Not given | W8: Active, not quotable (Rs 0) | X8: Category notes only (beds). No service-specific notes. | Y8: Y | Z8: Y | AB8: Unpriced, No B2B, GST basis, Knowledge | AC8: 0 | AD8: 1 | AE8: 1 | AF8: 1 | AG8: 0 | AH8: 1 | AI8: 0
A9: BED-SEMI | C9: Semi-Fowler Hospital Bed with Railings (Rental) | D9: beds | E9: Book My Medicare (BMM) | F9: Book My Medicare (BMM) | H9: day | I9: Daily rental. No monthly rental rate exists in any source; a month is not 30 day rates. | K9: 180 | M9: Not on the CRM rate card | N9: Not loaded | O9: 120 | P9: =IF(AND(ISNUMBER(J9),J9>0),ROUND(J9*Assumptions!$B$4,2),"") | Q9: =IF(AND(ISNUMBER(K9),ISNUMBER(O9)),IF(ROUND(K9*Assumptions!$B$4,2)=O9,"Equals 70%","Differs ("&TEXT(O9/K9,"0%")&" of B2C)"),"") -> Differs (67% of B2C) | R9: Not loaded. Draft B2B is unapproved. | T9: 18% GST | U9: Not confirmed: CRM basis is empty; draft gives a GST rate, not whether prices include it | V9: Not given | W9: Not loaded | X9: No service yet. Category notes (beds) would apply after import. | Y9: N | Z9: Y | AA9: BED-HOSP | AB9: GST basis, Knowledge, Possible overlap | AC9: 0 | AD9: 1 | AE9: 0 | AF9: 1 | AG9: 1 | AH9: 0 | AI9: 0
A10: TYNA-BED | B10: Tyna Bed / Positioning Alternating Mattress | C10: Tubular High-Risk Pressure Redistribution Bed | D10: beds | E10: Book My Medicare (BMM) | F10: Book My Medicare (BMM) | G10: day | H10: day | I10: Daily rental. No monthly rental rate exists in any source; a month is not 30 day rates. | J10: 0 | K10: 150 | M10: Not priced: Rs 0 placeholder, agents see "quote required" | N10: None (0 buying rates in CRM) | O10: 100 | P10: =IF(AND(ISNUMBER(J10),J10>0),ROUND(J10*Assumptions!$B$4,2),"") | Q10: =IF(AND(ISNUMBER(K10),ISNUMBER(O10)),IF(ROUND(K10*Assumptions!$B$4,2)=O10,"Equals 70%","Differs ("&TEXT(O10/K10,"0%")&" of B2C)"),"") -> Differs (67% of B2C) | R10: No buying rate, and none derivable: no selling price. Draft B2B is unapproved. | S10: Not set | T10: 18% GST | U10: Not confirmed: CRM basis is empty; draft gives a GST rate, not whether prices include it | V10: Not given | W10: Active, not quotable (Rs 0) | X10: Category notes only (beds). No service-specific notes. | Y10: Y | Z10: Y | AB10: Unpriced, No B2B, GST basis, Knowledge | AC10: 0 | AD10: 1 | AE10: 1 | AF10: 1 | AG10: 0 | AH10: 1 | AI10: 0
A11: ADULT-DIAP | C11: Adult Diapers Tape-Style (Pack of 10 Large) | D11: consumables | E11: Book My Medicare (BMM) | F11: Book My Medicare (BMM) | H11: box | I11: Only one source; unit as given | K11: 550 | M11: Not on the CRM rate card | N11: Not loaded | O11: 360 | P11: =IF(AND(ISNUMBER(J11),J11>0),ROUND(J11*Assumptions!$B$4,2),"") | Q11: =IF(AND(ISNUMBER(K11),ISNUMBER(O11)),IF(ROUND(K11*Assumptions!$B$4,2)=O11,"Equals 70%","Differs ("&TEXT(O11/K11,"0%")&" of B2C)"),"") -> Differs (65% of B2C) | R11: Not loaded. Draft B2B is unapproved. | T11: 12% GST | U11: Not confirmed: CRM basis is empty; draft gives a GST rate, not whether prices include it | V11: Not given | W11: Not loaded | X11: No service yet. Category notes (consumables) would apply after import. | Y11: N | Z11: Y | AB11: GST basis, Knowledge | AC11: 0 | AD11: 1 | AE11: 0 | AF11: 1 | AG11: 0 | AH11: 0 | AI11: 0
A12: BIPAP-MASK | C12: Full-Face Non-Vented BiPAP Cushion Mask | D12: consumables | E12: Book My Medicare (BMM) | F12: Book My Medicare (BMM) | H12: unit | I12: Only one source; unit as given | K12: 2800 | M12: Not on the CRM rate card | N12: Not loaded | O12: 1800 | P12: =IF(AND(ISNUMBER(J12),J12>0),ROUND(J12*Assumptions!$B$4,2),"") | Q12: =IF(AND(ISNUMBER(K12),ISNUMBER(O12)),IF(ROUND(K12*Assumptions!$B$4,2)=O12,"Equals 70%","Differs ("&TEXT(O12/K12,"0%")&" of B2C)"),"") -> Differs (64% of B2C) | R12: Not loaded. Draft B2B is unapproved. | T12: 12% GST | U12: Not confirmed: CRM basis is empty; draft gives a GST rate, not whether prices include it | V12: Not given | W12: Not loaded | X12: No service yet. Category notes (consumables) would apply after import. | Y12: N | Z12: Y | AB12: GST basis, Knowledge | AC12: 0 | AD12: 1 | AE12: 0 | AF12: 1 | AG12: 0 | AH12: 0 | AI12: 0
A13: CAVILON-SP | B13: 3M Cavilon No-Sting Barrier Film Spray | C13: 3M Cavilon No-Sting Barrier Film Spray (28ml) | D13: consumables | E13: Book My Medicare (BMM) | F13: Book My Medicare (BMM) | G13: unit | H13: unit | I13: Same unit | J13: 0 | K13: 1100 | M13: Not priced: Rs 0 placeholder, agents see "quote required" | N13: None (0 buying rates in CRM) | O13: 750 | P13: =IF(AND(ISNUMBER(J13),J13>0),ROUND(J13*Assumptions!$B$4,2),"") | Q13: =IF(AND(ISNUMBER(K13),ISNUMBER(O13)),IF(ROUND(K13*Assumptions!$B$4,2)=O13,"Equals 70%","Differs ("&TEXT(O13/K13,"0%")&" of B2C)"),"") -> Differs (68% of B2C) | R13: No buying rate, and none derivable: no selling price. Draft B2B is unapproved. | S13: Not set | T13: 12% GST | U13: Not confirmed: CRM basis is empty; draft gives a GST rate, not whether prices include it | V13: Not given | W13: Active, not quotable (Rs 0) | X13: Category notes only (consumables). No service-specific notes. | Y13: Y | Z13: Y | AB13: Unpriced, No B2B, GST basis, Knowledge | AC13: 0 | AD13: 1 | AE13: 1 | AF13: 1 | AG13: 0 | AH13: 1 | AI13: 0
A14: FEED-SYR-60 | B14: Feeding Syringe (Catheter Tip 50/60ml) | C14: Catheter-Tip Feeding Syringes (60ml, Pack of 5) | D14: consumables | E14: Book My Medicare (BMM) | F14: Book My Medicare (BMM) | G14: unit | H14: box | I14: Pack size differs: rate card sells one syringe ("unit"), draft sells a pack of 5 ("box"). Different product; never convert. | J14: 0 | K14: 280 | M14: Not priced: Rs 0 placeholder, agents see "quote required" | N14: None (0 buying rates in CRM) | O14: 170 | P14: =IF(AND(ISNUMBER(J14),J14>0),ROUND(J14*Assumptions!$B$4,2),"") | Q14: =IF(AND(ISNUMBER(K14),ISNUMBER(O14)),IF(ROUND(K14*Assumptions!$B$4,2)=O14,"Equals 70%","Differs ("&TEXT(O14/K14,"0%")&" of B2C)"),"") -> Differs (61% of B2C) | R14: No buying rate, and none derivable: no selling price. Draft B2B is unapproved. | S14: Not set | T14: 12% GST | U14: Not confirmed: CRM basis is empty; draft gives a GST rate, not whether prices include it | V14: Not given | W14: Active, not quotable (Rs 0) | X14: Category notes only (consumables). No service-specific notes. | Y14: Y | Z14: Y | AB14: Unit, Unpriced, No B2B, GST basis, Knowledge | AC14: 1 | AD14: 1 | AE14: 1 | AF14: 1 | AG14: 0 | AH14: 1 | AI14: 0
A15: FOLEY-CATH | C15: Silicone Foley Balloon Catheter (All Sizes) | D15: consumables | E15: Book My Medicare (BMM) | F15: Book My Medicare (BMM) | H15: unit | I15: Only one source; unit as given | K15: 320 | M15: Not on the CRM rate card | N15: Not loaded | O15: 190 | P15: =IF(AND(ISNUMBER(J15),J15>0),ROUND(J15*Assumptions!$B$4,2),"") | Q15: =IF(AND(ISNUMBER(K15),ISNUMBER(O15)),IF(ROUND(K15*Assumptions!$B$4,2)=O15,"Equals 70%","Differs ("&TEXT(O15/K15,"0%")&" of B2C)"),"") -> Differs (59% of B2C) | R15: Not loaded. Draft B2B is unapproved. | T15: 12% GST | U15: Not confirmed: CRM basis is empty; draft gives a GST rate, not whether prices include it | V15: Not given | W15: Not loaded | X15: No service yet. Category notes (consumables) would apply after import. | Y15: N | Z15: Y | AB15: GST basis, Knowledge | AC15: 0 | AD15: 1 | AE15: 0 | AF15: 1 | AG15: 0 | AH15: 0 | AI15: 0
A16: GLOVES-BOX | B16: Examination Gloves Box (100 pcs) | C16: Examination Gloves Box (Powder-Free, 100 pcs) | D16: consumables | E16: Book My Medicare (BMM) | F16: Book My Medicare (BMM) | G16: box | H16: box | I16: Same unit | J16: 0 | K16: 450 | M16: Not priced: Rs 0 placeholder, agents see "quote required" | N16: None (0 buying rates in CRM) | O16: 280 | P16: =IF(AND(ISNUMBER(J16),J16>0),ROUND(J16*Assumptions!$B$4,2),"") | Q16: =IF(AND(ISNUMBER(K16),ISNUMBER(O16)),IF(ROUND(K16*Assumptions!$B$4,2)=O16,"Equals 70%","Differs ("&TEXT(O16/K16,"0%")&" of B2C)"),"") -> Differs (62% of B2C) | R16: No buying rate, and none derivable: no selling price. Draft B2B is unapproved. | S16: Not set | T16: 12% GST | U16: Not confirmed: CRM basis is empty; draft gives a GST rate, not whether prices include it | V16: Not given | W16: Active, not quotable (Rs 0) | X16: Category notes only (consumables). No service-specific notes. | Y16: Y | Z16: Y | AB16: Unpriced, No B2B, GST basis, Knowledge | AC16: 0 | AD16: 1 | AE16: 1 | AF16: 1 | AG16: 0 | AH16: 1 | AI16: 0
A17: GLOVES-STER | C17: Surgical Sterile Gloves Pairs (Pack of 10) | D17: consumables | E17: Book My Medicare (BMM) | F17: Book My Medicare (BMM) | H17: box | I17: Only one source; unit as given | K17: 350 | M17: Not on the CRM rate card | N17: Not loaded | O17: 220 | P17: =IF(AND(ISNUMBER(J17),J17>0),ROUND(J17*Assumptions!$B$4,2),"") | Q17: =IF(AND(ISNUMBER(K17),ISNUMBER(O17)),IF(ROUND(K17*Assumptions!$B$4,2)=O17,"Equals 70%","Differs ("&TEXT(O17/K17,"0%")&" of B2C)"),"") -> Differs (63% of B2C) | R17: Not loaded. Draft B2B is unapproved. | T17: 12% GST | U17: Not confirmed: CRM basis is empty; draft gives a GST rate, not whether prices include it | V17: Not given | W17: Not loaded | X17: No service yet. Category notes (consumables) would apply after import. | Y17: N | Z17: Y | AB17: GST basis, Knowledge | AC17: 0 | AD17: 1 | AE17: 0 | AF17: 1 | AG17: 0 | AH17: 0 | AI17: 0
A18: HFNC-KIT | C18: Optiflow Nasal Interface & Heated Breathing Tube | D18: consumables | E18: Book My Medicare (BMM) | F18: Book My Medicare (BMM) | H18: unit | I18: Only one source; unit as given | K18: 4500 | M18: Not on the CRM rate card | N18: Not loaded | O18: 3100 | P18: =IF(AND(ISNUMBER(J18),J18>0),ROUND(J18*Assumptions!$B$4,2),"") | Q18: =IF(AND(ISNUMBER(K18),ISNUMBER(O18)),IF(ROUND(K18*Assumptions!$B$4,2)=O18,"Equals 70%","Differs ("&TEXT(O18/K18,"0%")&" of B2C)"),"") -> Differs (69% of B2C) | R18: Not loaded. Draft B2B is unapproved. | T18: 12% GST | U18: Not confirmed: CRM basis is empty; draft gives a GST rate, not whether prices include it | V18: Not given | W18: Not loaded | X18: No service yet. Category notes (consumables) would apply after import. | Y18: N | Z18: Y | AB18: GST basis, Knowledge | AC18: 0 | AD18: 1 | AE18: 0 | AF18: 1 | AG18: 0 | AH18: 0 | AI18: 0
A19: HME-FILTER | C19: Heat & Moisture Exchanger (HME) Filter Pack | D19: consumables | E19: Book My Medicare (BMM) | F19: Book My Medicare (BMM) | H19: box | I19: Only one source; unit as given | K19: 650 | M19: Not on the CRM rate card | N19: Not loaded | O19: 400 | P19: =IF(AND(ISNUMBER(J19),J19>0),ROUND(J19*Assumptions!$B$4,2),"") | Q19: =IF(AND(ISNUMBER(K19),ISNUMBER(O19)),IF(ROUND(K19*Assumptions!$B$4,2)=O19,"Equals 70%","Differs ("&TEXT(O19/K19,"0%")&" of B2C)"),"") -> Differs (62% of B2C) | R19: Not loaded. Draft B2B is unapproved. | T19: 12% GST | U19: Not confirmed: CRM basis is empty; draft gives a GST rate, not whether prices include it | V19: Not given | W19: Not loaded | X19: No service yet. Category notes (consumables) would apply after import. | Y19: N | Z19: Y | AB19: GST basis, Knowledge | AC19: 0 | AD19: 1 | AE19: 0 | AF19: 1 | AG19: 0 | AH19: 0 | AI19: 0
A20: IV-CAN-SET | C20: IV Infusion Administration Set with Micro-Drip | D20: consumables | E20: Book My Medicare (BMM) | F20: Book My Medicare (BMM) | H20: unit | I20: Only one source; unit as given | K20: 140 | M20: Not on the CRM rate card | N20: Not loaded | O20: 75 | P20: =IF(AND(ISNUMBER(J20),J20>0),ROUND(J20*Assumptions!$B$4,2),"") | Q20: =IF(AND(ISNUMBER(K20),ISNUMBER(O20)),IF(ROUND(K20*Assumptions!$B$4,2)=O20,"Equals 70%","Differs ("&TEXT(O20/K20,"0%")&" of B2C)"),"") -> Differs (54% of B2C) | R20: Not loaded. Draft B2B is unapproved. | T20: 12% GST | U20: Not confirmed: CRM basis is empty; draft gives a GST rate, not whether prices include it | V20: Not given | W20: Not loaded | X20: No service yet. Category notes (consumables) would apply after import. | Y20: N | Z20: Y | AB20: GST basis, Knowledge | AC20: 0 | AD20: 1 | AE20: 0 | AF20: 1 | AG20: 0 | AH20: 0 | AI20: 0
A21: MOIST-CREAM | B21: Moisturex Soft Skin Barrier Cream | C21: Moisturex Soft Protective Barrier Emollient Cream | D21: consumables | E21: Book My Medicare (BMM) | F21: Book My Medicare (BMM) | G21: unit | H21: unit | I21: Same unit | J21: 0 | K21: 380 | M21: Not priced: Rs 0 placeholder, agents see "quote required" | N21: None (0 buying rates in CRM) | O21: 240 | P21: =IF(AND(ISNUMBER(J21),J21>0),ROUND(J21*Assumptions!$B$4,2),"") | Q21: =IF(AND(ISNUMBER(K21),ISNUMBER(O21)),IF(ROUND(K21*Assumptions!$B$4,2)=O21,"Equals 70%","Differs ("&TEXT(O21/K21,"0%")&" of B2C)"),"") -> Differs (63% of B2C) | R21: No buying rate, and none derivable: no selling price. Draft B2B is unapproved. | S21: Not set | T21: 12% GST | U21: Not confirmed: CRM basis is empty; draft gives a GST rate, not whether prices include it | V21: Not given | W21: Active, not quotable (Rs 0) | X21: Category notes only (consumables). No service-specific notes. | Y21: Y | Z21: Y | AB21: Unpriced, No B2B, GST basis, Knowledge | AC21: 0 | AD21: 1 | AE21: 1 | AF21: 1 | AG21: 0 | AH21: 1 | AI21: 0
A22: MOUTH-CHX | B22: Chlorhexidine Mouthwash (Oral Care) | C22: Chlorhexidine Gluconate 0.2% Oral Care Rinse | D22: consumables | E22: Book My Medicare (BMM) | F22: Book My Medicare (BMM) | G22: unit | H22: unit | I22: Same unit | J22: 0 | K22: 160 | M22: Not priced: Rs 0 placeholder, agents see "quote required" | N22: None (0 buying rates in CRM) | O22: 95 | P22: =IF(AND(ISNUMBER(J22),J22>0),ROUND(J22*Assumptions!$B$4,2),"") | Q22: =IF(AND(ISNUMBER(K22),ISNUMBER(O22)),IF(ROUND(K22*Assumptions!$B$4,2)=O22,"Equals 70%","Differs ("&TEXT(O22/K22,"0%")&" of B2C)"),"") -> Differs (59% of B2C) | R22: No buying rate, and none derivable: no selling price. Draft B2B is unapproved. | S22: Not set | T22: 12% GST | U22: Not confirmed: CRM basis is empty; draft gives a GST rate, not whether prices include it | V22: Not given | W22: Active, not quotable (Rs 0) | X22: Category notes only (consumables). No service-specific notes. | Y22: Y | Z22: Y | AB22: Unpriced, No B2B, GST basis, Knowledge | AC22: 0 | AD22: 1 | AE22: 1 | AF22: 1 | AG22: 0 | AH22: 1 | AI22: 0
A23: OXY-CANNULA | C23: Nasal Oxygen Cannula with Twin Prong Tubing | D23: consumables | E23: Book My Medicare (BMM) | F23: Book My Medicare (BMM) | H23: unit | I23: Only one source; unit as given | K23: 150 | M23: Not on the CRM rate card | N23: Not loaded | O23: 85 | P23: =IF(AND(ISNUMBER(J23),J23>0),ROUND(J23*Assumptions!$B$4,2),"") | Q23: =IF(AND(ISNUMBER(K23),ISNUMBER(O23)),IF(ROUND(K23*Assumptions!$B$4,2)=O23,"Equals 70%","Differs ("&TEXT(O23/K23,"0%")&" of B2C)"),"") -> Differs (57% of B2C) | R23: Not loaded. Draft B2B is unapproved. | T23: 12% GST | U23: Not confirmed: CRM basis is empty; draft gives a GST rate, not whether prices include it | V23: Not given | W23: Not loaded | X23: No service yet. Category notes (consumables) would apply after import. | Y23: N | Z23: Y | AB23: GST basis, Knowledge | AC23: 0 | AD23: 1 | AE23: 0 | AF23: 1 | AG23: 0 | AH23: 0 | AI23: 0
A24: OXY-MASK | C24: Venturi / High-Concentration Oxygen Mask | D24: consumables | E24: Book My Medicare (BMM) | F24: Book My Medicare (BMM) | H24: unit | I24: Only one source; unit as given | K24: 240 | M24: Not on the CRM rate card | N24: Not loaded | O24: 140 | P24: =IF(AND(ISNUMBER(J24),J24>0),ROUND(J24*Assumptions!$B$4,2),"") | Q24: =IF(AND(ISNUMBER(K24),ISNUMBER(O24)),IF(ROUND(K24*Assumptions!$B$4,2)=O24,"Equals 70%","Differs ("&TEXT(O24/K24,"0%")&" of B2C)"),"") -> Differs (58% of B2C) | R24: Not loaded. Draft B2B is unapproved. | T24: 12% GST | U24: Not confirmed: CRM basis is empty; draft gives a GST rate, not whether prices include it | V24: Not given | W24: Not loaded | X24: No service yet. Category notes (consumables) would apply after import. | Y24: N | Z24: Y | AB24: GST basis, Knowledge | AC24: 0 | AD24: 1 | AE24: 0 | AF24: 1 | AG24: 0 | AH24: 0 | AI24: 0
A25: RYLE-TUBE | C25: Ryle's Nasogastric Feeding Tube with Guide Wire | D25: consumables | E25: Book My Medicare (BMM) | F25: Book My Medicare (BMM) | H25: unit | I25: Only one source; unit as given | K25: 220 | M25: Not on the CRM rate card | N25: Not loaded | O25: 130 | P25: =IF(AND(ISNUMBER(J25),J25>0),ROUND(J25*Assumptions!$B$4,2),"") | Q25: =IF(AND(ISNUMBER(K25),ISNUMBER(O25)),IF(ROUND(K25*Assumptions!$B$4,2)=O25,"Equals 70%","Differs ("&TEXT(O25/K25,"0%")&" of B2C)"),"") -> Differs (59% of B2C) | R25: Not loaded. Draft B2B is unapproved. | T25: 12% GST | U25: Not confirmed: CRM basis is empty; draft gives a GST rate, not whether prices include it | V25: Not given | W25: Not loaded | X25: No service yet. Category notes (consumables) would apply after import. | Y25: N | Z25: Y | AB25: GST basis, Knowledge | AC25: 0 | AD25: 1 | AE25: 0 | AF25: 1 | AG25: 0 | AH25: 0 | AI25: 0
A26: SUCT-CATH | C26: Mucus Extractor & Suction Catheters (10 pcs) | D26: consumables | E26: Book My Medicare (BMM) | F26: Book My Medicare (BMM) | H26: box | I26: Only one source; unit as given | K26: 220 | M26: Not on the CRM rate card | N26: Not loaded | O26: 130 | P26: =IF(AND(ISNUMBER(J26),J26>0),ROUND(J26*Assumptions!$B$4,2),"") | Q26: =IF(AND(ISNUMBER(K26),ISNUMBER(O26)),IF(ROUND(K26*Assumptions!$B$4,2)=O26,"Equals 70%","Differs ("&TEXT(O26/K26,"0%")&" of B2C)"),"") -> Differs (59% of B2C) | R26: Not loaded. Draft B2B is unapproved. | T26: 12% GST | U26: Not confirmed: CRM basis is empty; draft gives a GST rate, not whether prices include it | V26: Not given | W26: Not loaded | X26: No service yet. Category notes (consumables) would apply after import. | Y26: N | Z26: Y | AB26: GST basis, Knowledge | AC26: 0 | AD26: 1 | AE26: 0 | AF26: 1 | AG26: 0 | AH26: 0 | AI26: 0
A27: TRACH-TUBE | C27: Cuffed / Uncuffed Tracheostomy Tube (Shiley Type) | D27: consumables | E27: Book My Medicare (BMM) | F27: Book My Medicare (BMM) | H27: unit | I27: Only one source; unit as given | K27: 1950 | M27: Not on the CRM rate card | N27: Not loaded | O27: 1300 | P27: =IF(AND(ISNUMBER(J27),J27>0),ROUND(J27*Assumptions!$B$4,2),"") | Q27: =IF(AND(ISNUMBER(K27),ISNUMBER(O27)),IF(ROUND(K27*Assumptions!$B$4,2)=O27,"Equals 70%","Differs ("&TEXT(O27/K27,"0%")&" of B2C)"),"") -> Differs (67% of B2C) | R27: Not loaded. Draft B2B is unapproved. | T27: 12% GST | U27: Not confirmed: CRM basis is empty; draft gives a GST rate, not whether prices include it | V27: Not given | W27: Not loaded | X27: No service yet. Category notes (consumables) would apply after import. | Y27: N | Z27: Y | AB27: GST basis, Knowledge | AC27: 0 | AD27: 1 | AE27: 0 | AF27: 1 | AG27: 0 | AH27: 0 | AI27: 0
A28: UNDER-PAD | C28: Super-Absorbent Bed Underpads (Pack of 10) | D28: consumables | E28: Book My Medicare (BMM) | F28: Book My Medicare (BMM) | H28: box | I28: Only one source; unit as given | K28: 420 | M28: Not on the CRM rate card | N28: Not loaded | O28: 260 | P28: =IF(AND(ISNUMBER(J28),J28>0),ROUND(J28*Assumptions!$B$4,2),"") | Q28: =IF(AND(ISNUMBER(K28),ISNUMBER(O28)),IF(ROUND(K28*Assumptions!$B$4,2)=O28,"Equals 70%","Differs ("&TEXT(O28/K28,"0%")&" of B2C)"),"") -> Differs (62% of B2C) | R28: Not loaded. Draft B2B is unapproved. | T28: 12% GST | U28: Not confirmed: CRM basis is empty; draft gives a GST rate, not whether prices include it | V28: Not given | W28: Not loaded | X28: No service yet. Category notes (consumables) would apply after import. | Y28: N | Z28: Y | AB28: GST basis, Knowledge | AC28: 0 | AD28: 1 | AE28: 0 | AF28: 1 | AG28: 0 | AH28: 0 | AI28: 0
A29: URO-BAG | C29: Urine Drainage Collection Bag with Anti-Reflux | D29: consumables | E29: Book My Medicare (BMM) | F29: Book My Medicare (BMM) | H29: unit | I29: Only one source; unit as given | K29: 180 | M29: Not on the CRM rate card | N29: Not loaded | O29: 95 | P29: =IF(AND(ISNUMBER(J29),J29>0),ROUND(J29*Assumptions!$B$4,2),"") | Q29: =IF(AND(ISNUMBER(K29),ISNUMBER(O29)),IF(ROUND(K29*Assumptions!$B$4,2)=O29,"Equals 70%","Differs ("&TEXT(O29/K29,"0%")&" of B2C)"),"") -> Differs (53% of B2C) | R29: Not loaded. Draft B2B is unapproved. | T29: 12% GST | U29: Not confirmed: CRM basis is empty; draft gives a GST rate, not whether prices include it | V29: Not given | W29: Not loaded | X29: No service yet. Category notes (consumables) would apply after import. | Y29: N | Z29: Y | AB29: GST basis, Knowledge | AC29: 0 | AD29: 1 | AE29: 0 | AF29: 1 | AG29: 0 | AH29: 0 | AI29: 0
A30: VENT-CIRCUIT | C30: Dual-Limb Ventilator Patient Circuit with Chamber | D30: consumables | E30: Book My Medicare (BMM) | F30: Book My Medicare (BMM) | H30: unit | I30: Only one source; unit as given | K30: 1800 | M30: Not on the CRM rate card | N30: Not loaded | O30: 1200 | P30: =IF(AND(ISNUMBER(J30),J30>0),ROUND(J30*Assumptions!$B$4,2),"") | Q30: =IF(AND(ISNUMBER(K30),ISNUMBER(O30)),IF(ROUND(K30*Assumptions!$B$4,2)=O30,"Equals 70%","Differs ("&TEXT(O30/K30,"0%")&" of B2C)"),"") -> Differs (67% of B2C) | R30: Not loaded. Draft B2B is unapproved. | T30: 12% GST | U30: Not confirmed: CRM basis is empty; draft gives a GST rate, not whether prices include it | V30: Not given | W30: Not loaded | X30: No service yet. Category notes (consumables) would apply after import. | Y30: N | Z30: Y | AB30: GST basis, Knowledge | AC30: 0 | AD30: 1 | AE30: 0 | AF30: 1 | AG30: 0 | AH30: 0 | AI30: 0
A31: ECG-12 | B31: ECG at home (12-lead) | C31: ECG at Home (12-Lead Diagnostic ECG) | D31: ecg | E31: SecondMedic (SM) | F31: SecondMedic (SM) | G31: unit | H31: test | I31: Rate card "unit" vs draft "test". The importer refuses the row until one wording is chosen. | J31: 900 | K31: 900 | M31: Price written by migration 20261008100500 (proposal deck). No in-app approval record or named approver in the repo. | N31: None (0 buying rates in CRM) | O31: 500 | P31: =IF(AND(ISNUMBER(J31),J31>0),ROUND(J31*Assumptions!$B$4,2),"") -> 630 | Q31: =IF(AND(ISNUMBER(K31),ISNUMBER(O31)),IF(ROUND(K31*Assumptions!$B$4,2)=O31,"Equals 70%","Differs ("&TEXT(O31/K31,"0%")&" of B2C)"),"") -> Differs (56% of B2C) | R31: No buying rate. The 70% rule can derive one at import from the selling price. Draft B2B is unapproved. | S31: Not set | T31: Exempt | U31: Not confirmed: CRM basis is empty; draft gives a GST rate, not whether prices include it | V31: Not given | W31: Active, quotable | X31: Category notes only (ecg). No service-specific notes. | Y31: Y | Z31: Y | AB31: Unit, No B2B, GST basis, Knowledge | AC31: 1 | AD31: 1 | AE31: 1 | AF31: 1 | AG31: 0 | AH31: 0 | AI31: 0
A32: ECG-RPT | C32: Follow-up / Repeat ECG at Home | D32: ecg | E32: SecondMedic (SM) | F32: SecondMedic (SM) | H32: test | I32: New item uses "test"; existing ecg services use "unit". Align the wording before import. | K32: 650 | M32: Not on the CRM rate card | N32: Not loaded | O32: 350 | P32: =IF(AND(ISNUMBER(J32),J32>0),ROUND(J32*Assumptions!$B$4,2),"") | Q32: =IF(AND(ISNUMBER(K32),ISNUMBER(O32)),IF(ROUND(K32*Assumptions!$B$4,2)=O32,"Equals 70%","Differs ("&TEXT(O32/K32,"0%")&" of B2C)"),"") -> Differs (54% of B2C) | R32: Not loaded. Draft B2B is unapproved. | T32: Exempt | U32: Not confirmed: CRM basis is empty; draft gives a GST rate, not whether prices include it | V32: Not given | W32: Not loaded | X32: No service yet. Category notes (ecg) would apply after import. | Y32: N | Z32: Y | AB32: Unit, GST basis, Knowledge | AC32: 1 | AD32: 1 | AE32: 0 | AF32: 1 | AG32: 0 | AH32: 0 | AI32: 0
A33: ATTEND-12H | B33: Attendant, 12-hour shift | C33: Trained Patient Attendant / Caretaker (12-Hour) | D33: eldercare | E33: Book My Medicare (BMM) | F33: Book My Medicare (BMM) | G33: shift | H33: shift | I33: 12-hour shift. Confirm "shift" means 12 hours for every provider. | J33: 0 | K33: 1200 | M33: Not priced: Rs 0 placeholder, agents see "quote required" | N33: None (0 buying rates in CRM) | O33: 900 | P33: =IF(AND(ISNUMBER(J33),J33>0),ROUND(J33*Assumptions!$B$4,2),"") | Q33: =IF(AND(ISNUMBER(K33),ISNUMBER(O33)),IF(ROUND(K33*Assumptions!$B$4,2)=O33,"Equals 70%","Differs ("&TEXT(O33/K33,"0%")&" of B2C)"),"") -> Differs (75% of B2C) | R33: No buying rate, and none derivable: no selling price. Draft B2B is unapproved. | S33: Not set | T33: Exempt | U33: Not confirmed: CRM basis is empty; draft gives a GST rate, not whether prices include it | V33: Not given | W33: Active, not quotable (Rs 0) | X33: Category notes only (eldercare). No service-specific notes. | Y33: Y | Z33: Y | AA33: ELDER-CARE | AB33: Unpriced, No B2B, GST basis, Knowledge, Possible overlap | AC33: 0 | AD33: 1 | AE33: 1 | AF33: 1 | AG33: 1 | AH33: 1 | AI33: 0
A34: ATTEND-24H | C34: Trained Patient Attendant / Caretaker (24-Hour) | D34: eldercare | E34: Book My Medicare (BMM) | F34: Book My Medicare (BMM) | H34: shift | I34: 24-hour cover labelled "shift", the same unit as the 12-hour services. Needs its own unit (e.g. "24 hours") before import. | K34: 2200 | M34: Not on the CRM rate card | N34: Not loaded | O34: 1650 | P34: =IF(AND(ISNUMBER(J34),J34>0),ROUND(J34*Assumptions!$B$4,2),"") | Q34: =IF(AND(ISNUMBER(K34),ISNUMBER(O34)),IF(ROUND(K34*Assumptions!$B$4,2)=O34,"Equals 70%","Differs ("&TEXT(O34/K34,"0%")&" of B2C)"),"") -> Differs (75% of B2C) | R34: Not loaded. Draft B2B is unapproved. | T34: Exempt | U34: Not confirmed: CRM basis is empty; draft gives a GST rate, not whether prices include it | V34: Not given | W34: Not loaded | X34: No service yet. Category notes (eldercare) would apply after import. | Y34: N | Z34: Y | AA34: ELDER-CARE | AB34: Unit, GST basis, Knowledge, Possible overlap | AC34: 1 | AD34: 1 | AE34: 0 | AF34: 1 | AG34: 1 | AH34: 0 | AI34: 0
A35: ELDER-CARE | B35: Elder care attendant | D35: eldercare | E35: Book My Medicare (BMM) | G35: unit | I35: Only one source; unit as given | J35: 0 | M35: Not priced: Rs 0 placeholder, agents see "quote required" | N35: None (0 buying rates in CRM) | P35: =IF(AND(ISNUMBER(J35),J35>0),ROUND(J35*Assumptions!$B$4,2),"") | Q35: =IF(AND(ISNUMBER(K35),ISNUMBER(O35)),IF(ROUND(K35*Assumptions!$B$4,2)=O35,"Equals 70%","Differs ("&TEXT(O35/K35,"0%")&" of B2C)"),"") | R35: No buying rate, and none derivable: no selling price. | S35: Not set | U35: Not confirmed: CRM basis is empty | V35: Not given | W35: Active, not quotable (Rs 0) | X35: Category notes only (eldercare). No service-specific notes. | Y35: Y | Z35: N | AA35: ATTEND-12H, ATTEND-24H | AB35: Unpriced, No B2B, GST basis, Knowledge, Possible overlap | AC35: 0 | AD35: 1 | AE35: 1 | AF35: 1 | AG35: 1 | AH35: 1 | AI35: 0
A36: AIRBED | B36: Air mattress, rental | C36: Alternating Pressure Bubble Air Mattress | D36: equipment | E36: Book My Medicare (BMM) | F36: Book My Medicare (BMM) | G36: day | H36: day | I36: Daily rental. No monthly rental rate exists in any source; a month is not 30 day rates. | J36: 0 | K36: 80 | M36: Not priced: Rs 0 placeholder, agents see "quote required" | N36: None (0 buying rates in CRM) | O36: 50 | P36: =IF(AND(ISNUMBER(J36),J36>0),ROUND(J36*Assumptions!$B$4,2),"") | Q36: =IF(AND(ISNUMBER(K36),ISNUMBER(O36)),IF(ROUND(K36*Assumptions!$B$4,2)=O36,"Equals 70%","Differs ("&TEXT(O36/K36,"0%")&" of B2C)"),"") -> Differs (63% of B2C) | R36: No buying rate, and none derivable: no selling price. Draft B2B is unapproved. | S36: Not set | T36: 18% GST | U36: Not confirmed: CRM basis is empty; draft gives a GST rate, not whether prices include it | V36: Not given | W36: Active, not quotable (Rs 0) | X36: Category notes only (equipment). No service-specific notes. | Y36: Y | Z36: Y | AB36: Unpriced, No B2B, GST basis, Knowledge | AC36: 0 | AD36: 1 | AE36: 1 | AF36: 1 | AG36: 0 | AH36: 1 | AI36: 0
A37: BIPAP-AUTO | C37: Auto BiPAP / CPAP Machine with Humidifier | D37: equipment | E37: Book My Medicare (BMM) | F37: Book My Medicare (BMM) | H37: day | I37: Daily rental. No monthly rental rate exists in any source; a month is not 30 day rates. | K37: 320 | M37: Not on the CRM rate card | N37: Not loaded | O37: 210 | P37: =IF(AND(ISNUMBER(J37),J37>0),ROUND(J37*Assumptions!$B$4,2),"") | Q37: =IF(AND(ISNUMBER(K37),ISNUMBER(O37)),IF(ROUND(K37*Assumptions!$B$4,2)=O37,"Equals 70%","Differs ("&TEXT(O37/K37,"0%")&" of B2C)"),"") -> Differs (66% of B2C) | R37: Not loaded. Draft B2B is unapproved. | T37: 12% GST | U37: Not confirmed: CRM basis is empty; draft gives a GST rate, not whether prices include it | V37: Not given | W37: Not loaded | X37: No service yet. Category notes (equipment) would apply after import. | Y37: N | Z37: Y | AA37: VENT-HOME | AB37: GST basis, Knowledge, Possible overlap | AC37: 0 | AD37: 1 | AE37: 0 | AF37: 1 | AG37: 1 | AH37: 0 | AI37: 0
A38: BP-MONITOR | B38: Blood Pressure Apparatus (Digital/Manual) | C38: Digital NIBP Blood Pressure Monitor | D38: equipment | E38: Book My Medicare (BMM) | F38: Book My Medicare (BMM) | G38: day | H38: day | I38: Daily rental. No monthly rental rate exists in any source; a month is not 30 day rates. | J38: 0 | K38: 50 | M38: Not priced: Rs 0 placeholder, agents see "quote required" | N38: None (0 buying rates in CRM) | O38: 30 | P38: =IF(AND(ISNUMBER(J38),J38>0),ROUND(J38*Assumptions!$B$4,2),"") | Q38: =IF(AND(ISNUMBER(K38),ISNUMBER(O38)),IF(ROUND(K38*Assumptions!$B$4,2)=O38,"Equals 70%","Differs ("&TEXT(O38/K38,"0%")&" of B2C)"),"") -> Differs (60% of B2C) | R38: No buying rate, and none derivable: no selling price. Draft B2B is unapproved. | S38: Not set | T38: 12% GST | U38: Not confirmed: CRM basis is empty; draft gives a GST rate, not whether prices include it | V38: Not given | W38: Active, not quotable (Rs 0) | X38: Category notes only (equipment). No service-specific notes. | Y38: Y | Z38: Y | AB38: Unpriced, No B2B, GST basis, Knowledge | AC38: 0 | AD38: 1 | AE38: 1 | AF38: 1 | AG38: 0 | AH38: 1 | AI38: 0
A39: GLUCOMETER | C39: Glucometer Device with Lancing Pen | D39: equipment | E39: Book My Medicare (BMM) | F39: Book My Medicare (BMM) | H39: unit | I39: Only one source; unit as given | K39: 950 | M39: Not on the CRM rate card | N39: Not loaded | O39: 620 | P39: =IF(AND(ISNUMBER(J39),J39>0),ROUND(J39*Assumptions!$B$4,2),"") | Q39: =IF(AND(ISNUMBER(K39),ISNUMBER(O39)),IF(ROUND(K39*Assumptions!$B$4,2)=O39,"Equals 70%","Differs ("&TEXT(O39/K39,"0%")&" of B2C)"),"") -> Differs (65% of B2C) | R39: Not loaded. Draft B2B is unapproved. | T39: 12% GST | U39: Not confirmed: CRM basis is empty; draft gives a GST rate, not whether prices include it | V39: Not given | W39: Not loaded | X39: No service yet. Category notes (equipment) would apply after import. | Y39: N | Z39: Y | AB39: GST basis, Knowledge | AC39: 0 | AD39: 1 | AE39: 0 | AF39: 1 | AG39: 0 | AH39: 0 | AI39: 0
A40: HFNC | B40: High-flow (HF) oxygen machine, rental | C40: High-Flow Nasal Cannula (Airvo 2) System | D40: equipment | E40: Book My Medicare (BMM) | F40: Book My Medicare (BMM) | G40: day | H40: day | I40: Daily rental. No monthly rental rate exists in any source; a month is not 30 day rates. | J40: 0 | K40: 1200 | M40: Not priced: Rs 0 placeholder, agents see "quote required" | N40: None (0 buying rates in CRM) | O40: 800 | P40: =IF(AND(ISNUMBER(J40),J40>0),ROUND(J40*Assumptions!$B$4,2),"") | Q40: =IF(AND(ISNUMBER(K40),ISNUMBER(O40)),IF(ROUND(K40*Assumptions!$B$4,2)=O40,"Equals 70%","Differs ("&TEXT(O40/K40,"0%")&" of B2C)"),"") -> Differs (67% of B2C) | R40: No buying rate, and none derivable: no selling price. Draft B2B is unapproved. | S40: Not set | T40: 12% GST | U40: Not confirmed: CRM basis is empty; draft gives a GST rate, not whether prices include it | V40: Not given | W40: Active, not quotable (Rs 0) | X40: Category notes only (equipment). No service-specific notes. | Y40: Y | Z40: Y | AB40: Unpriced, No B2B, GST basis, Knowledge | AC40: 0 | AD40: 1 | AE40: 1 | AF40: 1 | AG40: 0 | AH40: 1 | AI40: 0
A41: MONITOR | B41: Multipara monitor, rental | C41: Multipara Vital Signs Monitor (ECG, NIBP, SpO2, Temp) | D41: equipment | E41: Book My Medicare (BMM) | F41: Book My Medicare (BMM) | G41: day | H41: day | I41: Daily rental. No monthly rental rate exists in any source; a month is not 30 day rates. | J41: 0 | K41: 300 | M41: Not priced: Rs 0 placeholder, agents see "quote required" | N41: None (0 buying rates in CRM) | O41: 190 | P41: =IF(AND(ISNUMBER(J41),J41>0),ROUND(J41*Assumptions!$B$4,2),"") | Q41: =IF(AND(ISNUMBER(K41),ISNUMBER(O41)),IF(ROUND(K41*Assumptions!$B$4,2)=O41,"Equals 70%","Differs ("&TEXT(O41/K41,"0%")&" of B2C)"),"") -> Differs (63% of B2C) | R41: No buying rate, and none derivable: no selling price. Draft B2B is unapproved. | S41: Not set | T41: 12% GST | U41: Not confirmed: CRM basis is empty; draft gives a GST rate, not whether prices include it | V41: Not given | W41: Active, not quotable (Rs 0) | X41: Category notes only (equipment). No service-specific notes. | Y41: Y | Z41: Y | AB41: Unpriced, No B2B, GST basis, Knowledge | AC41: 0 | AD41: 1 | AE41: 1 | AF41: 1 | AG41: 0 | AH41: 1 | AI41: 0
A42: NEBULIZER | C42: Medical Compressor Nebulizer Machine | D42: equipment | E42: Book My Medicare (BMM) | F42: Book My Medicare (BMM) | H42: day | I42: Daily rental. No monthly rental rate exists in any source; a month is not 30 day rates. | K42: 60 | M42: Not on the CRM rate card | N42: Not loaded | O42: 35 | P42: =IF(AND(ISNUMBER(J42),J42>0),ROUND(J42*Assumptions!$B$4,2),"") | Q42: =IF(AND(ISNUMBER(K42),ISNUMBER(O42)),IF(ROUND(K42*Assumptions!$B$4,2)=O42,"Equals 70%","Differs ("&TEXT(O42/K42,"0%")&" of B2C)"),"") -> Differs (58% of B2C) | R42: Not loaded. Draft B2B is unapproved. | T42: 12% GST | U42: Not confirmed: CRM basis is empty; draft gives a GST rate, not whether prices include it | V42: Not given | W42: Not loaded | X42: No service yet. Category notes (equipment) would apply after import. | Y42: N | Z42: Y | AB42: GST basis, Knowledge | AC42: 0 | AD42: 1 | AE42: 0 | AF42: 1 | AG42: 0 | AH42: 0 | AI42: 0
A43: OXY-CONC | B43: Oxygen concentrator, rental | D43: equipment | E43: Book My Medicare (BMM) | G43: day | I43: Daily rental. No monthly rental rate exists in any source; a month is not 30 day rates. | J43: 0 | M43: Not priced: Rs 0 placeholder, agents see "quote required" | N43: None (0 buying rates in CRM) | P43: =IF(AND(ISNUMBER(J43),J43>0),ROUND(J43*Assumptions!$B$4,2),"") | Q43: =IF(AND(ISNUMBER(K43),ISNUMBER(O43)),IF(ROUND(K43*Assumptions!$B$4,2)=O43,"Equals 70%","Differs ("&TEXT(O43/K43,"0%")&" of B2C)"),"") | R43: No buying rate, and none derivable: no selling price. | S43: Not set | U43: Not confirmed: CRM basis is empty | V43: Not given | W43: Active, not quotable (Rs 0) | X43: Category notes only (equipment). No service-specific notes. | Y43: Y | Z43: N | AA43: OXY-CONC5, OXY-CONC10 | AB43: Unpriced, No B2B, GST basis, Knowledge, Possible overlap | AC43: 0 | AD43: 1 | AE43: 1 | AF43: 1 | AG43: 1 | AH43: 1 | AI43: 0
A44: OXY-CONC10 | C44: Oxygen Concentrator 10 Litre High Flow | D44: equipment | E44: Book My Medicare (BMM) | F44: Book My Medicare (BMM) | H44: day | I44: Daily rental. No monthly rental rate exists in any source; a month is not 30 day rates. | K44: 380 | M44: Not on the CRM rate card | N44: Not loaded | O44: 250 | P44: =IF(AND(ISNUMBER(J44),J44>0),ROUND(J44*Assumptions!$B$4,2),"") | Q44: =IF(AND(ISNUMBER(K44),ISNUMBER(O44)),IF(ROUND(K44*Assumptions!$B$4,2)=O44,"Equals 70%","Differs ("&TEXT(O44/K44,"0%")&" of B2C)"),"") -> Differs (66% of B2C) | R44: Not loaded. Draft B2B is unapproved. | T44: 12% GST | U44: Not confirmed: CRM basis is empty; draft gives a GST rate, not whether prices include it | V44: Not given | W44: Not loaded | X44: No service yet. Category notes (equipment) would apply after import. | Y44: N | Z44: Y | AA44: OXY-CONC | AB44: GST basis, Knowledge, Possible overlap | AC44: 0 | AD44: 1 | AE44: 0 | AF44: 1 | AG44: 1 | AH44: 0 | AI44: 0
A45: OXY-CONC5 | C45: Oxygen Concentrator 5 Litre (Medical Grade) | D45: equipment | E45: Book My Medicare (BMM) | F45: Book My Medicare (BMM) | H45: day | I45: Daily rental. No monthly rental rate exists in any source; a month is not 30 day rates. | K45: 200 | M45: Not on the CRM rate card | N45: Not loaded | O45: 130 | P45: =IF(AND(ISNUMBER(J45),J45>0),ROUND(J45*Assumptions!$B$4,2),"") | Q45: =IF(AND(ISNUMBER(K45),ISNUMBER(O45)),IF(ROUND(K45*Assumptions!$B$4,2)=O45,"Equals 70%","Differs ("&TEXT(O45/K45,"0%")&" of B2C)"),"") -> Differs (65% of B2C) | R45: Not loaded. Draft B2B is unapproved. | T45: 12% GST | U45: Not confirmed: CRM basis is empty; draft gives a GST rate, not whether prices include it | V45: Not given | W45: Not loaded | X45: No service yet. Category notes (equipment) would apply after import. | Y45: N | Z45: Y | AA45: OXY-CONC | AB45: GST basis, Knowledge, Possible overlap | AC45: 0 | AD45: 1 | AE45: 0 | AF45: 1 | AG45: 1 | AH45: 0 | AI45: 0
A46: OXY-CYL | B46: Oxygen Cylinder (with Regulator & Flowmeter) | D46: equipment | E46: Book My Medicare (BMM) | G46: day | I46: Daily rental. No monthly rental rate exists in any source; a month is not 30 day rates. | J46: 0 | M46: Not priced: Rs 0 placeholder, agents see "quote required" | N46: None (0 buying rates in CRM) | P46: =IF(AND(ISNUMBER(J46),J46>0),ROUND(J46*Assumptions!$B$4,2),"") | Q46: =IF(AND(ISNUMBER(K46),ISNUMBER(O46)),IF(ROUND(K46*Assumptions!$B$4,2)=O46,"Equals 70%","Differs ("&TEXT(O46/K46,"0%")&" of B2C)"),"") | R46: No buying rate, and none derivable: no selling price. | S46: Not set | U46: Not confirmed: CRM basis is empty | V46: Not given | W46: Active, not quotable (Rs 0) | X46: Category notes only (equipment). No service-specific notes. | Y46: Y | Z46: N | AA46: OXY-CYL-D, OXY-CYL-B | AB46: Unpriced, No B2B, GST basis, Knowledge, Possible overlap | AC46: 0 | AD46: 1 | AE46: 1 | AF46: 1 | AG46: 1 | AH46: 1 | AI46: 0
A47: OXY-CYL-B | C47: Oxygen Cylinder Portable B-Type (10L Refillable) | D47: equipment | E47: Book My Medicare (BMM) | F47: Book My Medicare (BMM) | H47: day | I47: Daily rental. No monthly rental rate exists in any source; a month is not 30 day rates. | K47: 80 | M47: Not on the CRM rate card | N47: Not loaded | O47: 50 | P47: =IF(AND(ISNUMBER(J47),J47>0),ROUND(J47*Assumptions!$B$4,2),"") | Q47: =IF(AND(ISNUMBER(K47),ISNUMBER(O47)),IF(ROUND(K47*Assumptions!$B$4,2)=O47,"Equals 70%","Differs ("&TEXT(O47/K47,"0%")&" of B2C)"),"") -> Differs (63% of B2C) | R47: Not loaded. Draft B2B is unapproved. | T47: 12% GST | U47: Not confirmed: CRM basis is empty; draft gives a GST rate, not whether prices include it | V47: Not given | W47: Not loaded | X47: No service yet. Category notes (equipment) would apply after import. | Y47: N | Z47: Y | AA47: OXY-CYL | AB47: GST basis, Knowledge, Possible overlap | AC47: 0 | AD47: 1 | AE47: 0 | AF47: 1 | AG47: 1 | AH47: 0 | AI47: 0
A48: OXY-CYL-D | C48: Oxygen Cylinder Jumbo D-Type (Bulk 46.7L) | D48: equipment | E48: Book My Medicare (BMM) | F48: Book My Medicare (BMM) | H48: day | I48: Daily rental. No monthly rental rate exists in any source; a month is not 30 day rates. | K48: 120 | M48: Not on the CRM rate card | N48: Not loaded | O48: 75 | P48: =IF(AND(ISNUMBER(J48),J48>0),ROUND(J48*Assumptions!$B$4,2),"") | Q48: =IF(AND(ISNUMBER(K48),ISNUMBER(O48)),IF(ROUND(K48*Assumptions!$B$4,2)=O48,"Equals 70%","Differs ("&TEXT(O48/K48,"0%")&" of B2C)"),"") -> Differs (63% of B2C) | R48: Not loaded. Draft B2B is unapproved. | T48: 12% GST | U48: Not confirmed: CRM basis is empty; draft gives a GST rate, not whether prices include it | V48: Not given | W48: Not loaded | X48: No service yet. Category notes (equipment) would apply after import. | Y48: N | Z48: Y | AA48: OXY-CYL | AB48: GST basis, Knowledge, Possible overlap | AC48: 0 | AD48: 1 | AE48: 0 | AF48: 1 | AG48: 1 | AH48: 0 | AI48: 0
A49: OXY-REFILL | C49: Oxygen Gas Refill (Medical Grade D-Type) | D49: equipment | E49: Book My Medicare (BMM) | F49: Book My Medicare (BMM) | H49: unit | I49: Only one source; unit as given | K49: 750 | M49: Not on the CRM rate card | N49: Not loaded | O49: 500 | P49: =IF(AND(ISNUMBER(J49),J49>0),ROUND(J49*Assumptions!$B$4,2),"") | Q49: =IF(AND(ISNUMBER(K49),ISNUMBER(O49)),IF(ROUND(K49*Assumptions!$B$4,2)=O49,"Equals 70%","Differs ("&TEXT(O49/K49,"0%")&" of B2C)"),"") -> Differs (67% of B2C) | R49: Not loaded. Draft B2B is unapproved. | T49: 12% GST | U49: Not confirmed: CRM basis is empty; draft gives a GST rate, not whether prices include it | V49: Not given | W49: Not loaded | X49: No service yet. Category notes (equipment) would apply after import. | Y49: N | Z49: Y | AB49: GST basis, Knowledge | AC49: 0 | AD49: 1 | AE49: 0 | AF49: 1 | AG49: 0 | AH49: 0 | AI49: 0
A50: PAT-LIFT | C50: Hydraulic Patient Transfer Hoist / Lift | D50: equipment | E50: Book My Medicare (BMM) | F50: Book My Medicare (BMM) | H50: day | I50: Daily rental. No monthly rental rate exists in any source; a month is not 30 day rates. | K50: 400 | M50: Not on the CRM rate card | N50: Not loaded | O50: 260 | P50: =IF(AND(ISNUMBER(J50),J50>0),ROUND(J50*Assumptions!$B$4,2),"") | Q50: =IF(AND(ISNUMBER(K50),ISNUMBER(O50)),IF(ROUND(K50*Assumptions!$B$4,2)=O50,"Equals 70%","Differs ("&TEXT(O50/K50,"0%")&" of B2C)"),"") -> Differs (65% of B2C) | R50: Not loaded. Draft B2B is unapproved. | T50: 18% GST | U50: Not confirmed: CRM basis is empty; draft gives a GST rate, not whether prices include it | V50: Not given | W50: Not loaded | X50: No service yet. Category notes (equipment) would apply after import. | Y50: N | Z50: Y | AB50: GST basis, Knowledge | AC50: 0 | AD50: 1 | AE50: 0 | AF50: 1 | AG50: 0 | AH50: 0 | AI50: 0
A51: SPO2-PROBE | B51: Pulse Oximeter / SpO2 Probe | C51: Finger Pulse Oximeter with OLED Display | D51: equipment | E51: Book My Medicare (BMM) | F51: Book My Medicare (BMM) | G51: day | H51: day | I51: Daily rental. No monthly rental rate exists in any source; a month is not 30 day rates. | J51: 0 | K51: 40 | M51: Not priced: Rs 0 placeholder, agents see "quote required" | N51: None (0 buying rates in CRM) | O51: 25 | P51: =IF(AND(ISNUMBER(J51),J51>0),ROUND(J51*Assumptions!$B$4,2),"") | Q51: =IF(AND(ISNUMBER(K51),ISNUMBER(O51)),IF(ROUND(K51*Assumptions!$B$4,2)=O51,"Equals 70%","Differs ("&TEXT(O51/K51,"0%")&" of B2C)"),"") -> Differs (63% of B2C) | R51: No buying rate, and none derivable: no selling price. Draft B2B is unapproved. | S51: Not set | T51: 12% GST | U51: Not confirmed: CRM basis is empty; draft gives a GST rate, not whether prices include it | V51: Not given | W51: Active, not quotable (Rs 0) | X51: Category notes only (equipment). No service-specific notes. | Y51: Y | Z51: Y | AB51: Unpriced, No B2B, GST basis, Knowledge | AC51: 0 | AD51: 1 | AE51: 1 | AF51: 1 | AG51: 0 | AH51: 1 | AI51: 0
A52: SUCTION | B52: Suction machine, rental | C52: Electric Medical Suction Machine (Single/Dual Jar) | D52: equipment | E52: Book My Medicare (BMM) | F52: Book My Medicare (BMM) | G52: day | H52: day | I52: Daily rental. No monthly rental rate exists in any source; a month is not 30 day rates. | J52: 0 | K52: 120 | M52: Not priced: Rs 0 placeholder, agents see "quote required" | N52: None (0 buying rates in CRM) | O52: 75 | P52: =IF(AND(ISNUMBER(J52),J52>0),ROUND(J52*Assumptions!$B$4,2),"") | Q52: =IF(AND(ISNUMBER(K52),ISNUMBER(O52)),IF(ROUND(K52*Assumptions!$B$4,2)=O52,"Equals 70%","Differs ("&TEXT(O52/K52,"0%")&" of B2C)"),"") -> Differs (63% of B2C) | R52: No buying rate, and none derivable: no selling price. Draft B2B is unapproved. | S52: Not set | T52: 12% GST | U52: Not confirmed: CRM basis is empty; draft gives a GST rate, not whether prices include it | V52: Not given | W52: Active, not quotable (Rs 0) | X52: Category notes only (equipment). No service-specific notes. | Y52: Y | Z52: Y | AB52: Unpriced, No B2B, GST basis, Knowledge | AC52: 0 | AD52: 1 | AE52: 1 | AF52: 1 | AG52: 0 | AH52: 1 | AI52: 0
A53: SYR-PUMP | C53: Precision Syringe Infusion Pump (Rental) | D53: equipment | E53: Book My Medicare (BMM) | F53: Book My Medicare (BMM) | H53: day | I53: Daily rental. No monthly rental rate exists in any source; a month is not 30 day rates. | K53: 250 | M53: Not on the CRM rate card | N53: Not loaded | O53: 160 | P53: =IF(AND(ISNUMBER(J53),J53>0),ROUND(J53*Assumptions!$B$4,2),"") | Q53: =IF(AND(ISNUMBER(K53),ISNUMBER(O53)),IF(ROUND(K53*Assumptions!$B$4,2)=O53,"Equals 70%","Differs ("&TEXT(O53/K53,"0%")&" of B2C)"),"") -> Differs (64% of B2C) | R53: Not loaded. Draft B2B is unapproved. | T53: 12% GST | U53: Not confirmed: CRM basis is empty; draft gives a GST rate, not whether prices include it | V53: Not given | W53: Not loaded | X53: No service yet. Category notes (equipment) would apply after import. | Y53: N | Z53: Y | AB53: GST basis, Knowledge | AC53: 0 | AD53: 1 | AE53: 0 | AF53: 1 | AG53: 0 | AH53: 0 | AI53: 0
A54: THERMO-DIG | B54: Clinical Digital Thermometer | C54: Clinical Digital Thermometer | D54: equipment | E54: Book My Medicare (BMM) | F54: Book My Medicare (BMM) | G54: unit | H54: unit | I54: Same unit | J54: 0 | K54: 250 | M54: Not priced: Rs 0 placeholder, agents see "quote required" | N54: None (0 buying rates in CRM) | O54: 160 | P54: =IF(AND(ISNUMBER(J54),J54>0),ROUND(J54*Assumptions!$B$4,2),"") | Q54: =IF(AND(ISNUMBER(K54),ISNUMBER(O54)),IF(ROUND(K54*Assumptions!$B$4,2)=O54,"Equals 70%","Differs ("&TEXT(O54/K54,"0%")&" of B2C)"),"") -> Differs (64% of B2C) | R54: No buying rate, and none derivable: no selling price. Draft B2B is unapproved. | S54: Not set | T54: 12% GST | U54: Not confirmed: CRM basis is empty; draft gives a GST rate, not whether prices include it | V54: Not given | W54: Active, not quotable (Rs 0) | X54: Category notes only (equipment). No service-specific notes. | Y54: Y | Z54: Y | AB54: Unpriced, No B2B, GST basis, Knowledge | AC54: 0 | AD54: 1 | AE54: 1 | AF54: 1 | AG54: 0 | AH54: 1 | AI54: 0
A55: VOL-PUMP | C55: Volumetric IV Infusion Pump (Rental) | D55: equipment | E55: Book My Medicare (BMM) | F55: Book My Medicare (BMM) | H55: day | I55: Daily rental. No monthly rental rate exists in any source; a month is not 30 day rates. | K55: 280 | M55: Not on the CRM rate card | N55: Not loaded | O55: 180 | P55: =IF(AND(ISNUMBER(J55),J55>0),ROUND(J55*Assumptions!$B$4,2),"") | Q55: =IF(AND(ISNUMBER(K55),ISNUMBER(O55)),IF(ROUND(K55*Assumptions!$B$4,2)=O55,"Equals 70%","Differs ("&TEXT(O55/K55,"0%")&" of B2C)"),"") -> Differs (64% of B2C) | R55: Not loaded. Draft B2B is unapproved. | T55: 12% GST | U55: Not confirmed: CRM basis is empty; draft gives a GST rate, not whether prices include it | V55: Not given | W55: Not loaded | X55: No service yet. Category notes (equipment) would apply after import. | Y55: N | Z55: Y | AB55: GST basis, Knowledge | AC55: 0 | AD55: 1 | AE55: 0 | AF55: 1 | AG55: 0 | AH55: 0 | AI55: 0
A56: WALK-STICK | C56: Quadripod Walking Stick (Wide Base) | D56: equipment | E56: Book My Medicare (BMM) | F56: Book My Medicare (BMM) | H56: unit | I56: Only one source; unit as given | K56: 650 | M56: Not on the CRM rate card | N56: Not loaded | O56: 420 | P56: =IF(AND(ISNUMBER(J56),J56>0),ROUND(J56*Assumptions!$B$4,2),"") | Q56: =IF(AND(ISNUMBER(K56),ISNUMBER(O56)),IF(ROUND(K56*Assumptions!$B$4,2)=O56,"Equals 70%","Differs ("&TEXT(O56/K56,"0%")&" of B2C)"),"") -> Differs (65% of B2C) | R56: Not loaded. Draft B2B is unapproved. | T56: 12% GST | U56: Not confirmed: CRM basis is empty; draft gives a GST rate, not whether prices include it | V56: Not given | W56: Not loaded | X56: No service yet. Category notes (equipment) would apply after import. | Y56: N | Z56: Y | AB56: GST basis, Knowledge | AC56: 0 | AD56: 1 | AE56: 0 | AF56: 1 | AG56: 0 | AH56: 0 | AI56: 0
A57: WALKER-ADJ | C57: Foldable Height-Adjustable Adult Walker | D57: equipment | E57: Book My Medicare (BMM) | F57: Book My Medicare (BMM) | H57: unit | I57: Only one source; unit as given | K57: 1400 | M57: Not on the CRM rate card | N57: Not loaded | O57: 900 | P57: =IF(AND(ISNUMBER(J57),J57>0),ROUND(J57*Assumptions!$B$4,2),"") | Q57: =IF(AND(ISNUMBER(K57),ISNUMBER(O57)),IF(ROUND(K57*Assumptions!$B$4,2)=O57,"Equals 70%","Differs ("&TEXT(O57/K57,"0%")&" of B2C)"),"") -> Differs (64% of B2C) | R57: Not loaded. Draft B2B is unapproved. | T57: 12% GST | U57: Not confirmed: CRM basis is empty; draft gives a GST rate, not whether prices include it | V57: Not given | W57: Not loaded | X57: No service yet. Category notes (equipment) would apply after import. | Y57: N | Z57: Y | AB57: GST basis, Knowledge | AC57: 0 | AD57: 1 | AE57: 0 | AF57: 1 | AG57: 0 | AH57: 0 | AI57: 0
A58: WHEEL-COMM | C58: Commode Wheelchair with Removable Pan | D58: equipment | E58: Book My Medicare (BMM) | F58: Book My Medicare (BMM) | H58: day | I58: Daily rental. No monthly rental rate exists in any source; a month is not 30 day rates. | K58: 90 | M58: Not on the CRM rate card | N58: Not loaded | O58: 55 | P58: =IF(AND(ISNUMBER(J58),J58>0),ROUND(J58*Assumptions!$B$4,2),"") | Q58: =IF(AND(ISNUMBER(K58),ISNUMBER(O58)),IF(ROUND(K58*Assumptions!$B$4,2)=O58,"Equals 70%","Differs ("&TEXT(O58/K58,"0%")&" of B2C)"),"") -> Differs (61% of B2C) | R58: Not loaded. Draft B2B is unapproved. | T58: 12% GST | U58: Not confirmed: CRM basis is empty; draft gives a GST rate, not whether prices include it | V58: Not given | W58: Not loaded | X58: No service yet. Category notes (equipment) would apply after import. | Y58: N | Z58: Y | AB58: GST basis, Knowledge | AC58: 0 | AD58: 1 | AE58: 0 | AF58: 1 | AG58: 0 | AH58: 0 | AI58: 0
A59: WHEEL-STD | C59: Standard Folding Wheelchair (Rental) | D59: equipment | E59: Book My Medicare (BMM) | F59: Book My Medicare (BMM) | H59: day | I59: Daily rental. No monthly rental rate exists in any source; a month is not 30 day rates. | K59: 70 | M59: Not on the CRM rate card | N59: Not loaded | O59: 40 | P59: =IF(AND(ISNUMBER(J59),J59>0),ROUND(J59*Assumptions!$B$4,2),"") | Q59: =IF(AND(ISNUMBER(K59),ISNUMBER(O59)),IF(ROUND(K59*Assumptions!$B$4,2)=O59,"Equals 70%","Differs ("&TEXT(O59/K59,"0%")&" of B2C)"),"") -> Differs (57% of B2C) | R59: Not loaded. Draft B2B is unapproved. | T59: 12% GST | U59: Not confirmed: CRM basis is empty; draft gives a GST rate, not whether prices include it | V59: Not given | W59: Not loaded | X59: No service yet. Category notes (equipment) would apply after import. | Y59: N | Z59: Y | AB59: GST basis, Knowledge | AC59: 0 | AD59: 1 | AE59: 0 | AF59: 1 | AG59: 0 | AH59: 0 | AI59: 0
A60: HOMECARE | B60: Other home healthcare service | D60: homecare | E60: Book My Medicare (BMM) | G60: unit | I60: Only one source; unit as given | J60: 0 | M60: Not priced: Rs 0 placeholder, agents see "quote required" | N60: None (0 buying rates in CRM) | P60: =IF(AND(ISNUMBER(J60),J60>0),ROUND(J60*Assumptions!$B$4,2),"") | Q60: =IF(AND(ISNUMBER(K60),ISNUMBER(O60)),IF(ROUND(K60*Assumptions!$B$4,2)=O60,"Equals 70%","Differs ("&TEXT(O60/K60,"0%")&" of B2C)"),"") | R60: No buying rate, and none derivable: no selling price. | S60: Not set | U60: Not confirmed: CRM basis is empty | V60: Not given | W60: Active, not quotable (Rs 0) | X60: Category notes only (homecare). No service-specific notes. | Y60: Y | Z60: N | AB60: Unpriced, No B2B, GST basis, Knowledge | AC60: 0 | AD60: 1 | AE60: 1 | AF60: 1 | AG60: 0 | AH60: 1 | AI60: 0
A61: MINI-ICU | B61: Mini-ICU setup at home | C61: Complete Mini-ICU Home Setup (Bed+Vent+Monitor) | D61: icu | E61: Book My Medicare (BMM) | F61: Book My Medicare (BMM) | G61: setup | H61: setup | I61: Same unit | J61: 0 | K61: 15000 | M61: Not priced: Rs 0 placeholder, agents see "quote required" | N61: None (0 buying rates in CRM) | O61: 10500 | P61: =IF(AND(ISNUMBER(J61),J61>0),ROUND(J61*Assumptions!$B$4,2),"") | Q61: =IF(AND(ISNUMBER(K61),ISNUMBER(O61)),IF(ROUND(K61*Assumptions!$B$4,2)=O61,"Equals 70%","Differs ("&TEXT(O61/K61,"0%")&" of B2C)"),"") -> Equals 70% | R61: No buying rate, and none derivable: no selling price. Draft B2B is unapproved. | S61: Not set | T61: 18% GST | U61: Not confirmed: CRM basis is empty; draft gives a GST rate, not whether prices include it | V61: Not given | W61: Active, not quotable (Rs 0) | X61: Category notes only (icu). No service-specific notes. | Y61: Y | Z61: Y | AB61: Unpriced, No B2B, GST basis, Knowledge | AC61: 0 | AD61: 1 | AE61: 1 | AF61: 1 | AG61: 0 | AH61: 1 | AI61: 0
A62: VENT-HOME | B62: Home ventilator (BiPAP / ventilator), rental | C62: Home Invasive/Non-Invasive Mechanical Ventilator | D62: icu | E62: Book My Medicare (BMM) | F62: Book My Medicare (BMM) | G62: day | H62: day | I62: Daily rental. No monthly rental rate exists in any source; a month is not 30 day rates. | J62: 0 | K62: 3500 | M62: Not priced: Rs 0 placeholder, agents see "quote required" | N62: None (0 buying rates in CRM) | O62: 2300 | P62: =IF(AND(ISNUMBER(J62),J62>0),ROUND(J62*Assumptions!$B$4,2),"") | Q62: =IF(AND(ISNUMBER(K62),ISNUMBER(O62)),IF(ROUND(K62*Assumptions!$B$4,2)=O62,"Equals 70%","Differs ("&TEXT(O62/K62,"0%")&" of B2C)"),"") -> Differs (66% of B2C) | R62: No buying rate, and none derivable: no selling price. Draft B2B is unapproved. | S62: Not set | T62: 12% GST | U62: Not confirmed: CRM basis is empty; draft gives a GST rate, not whether prices include it | V62: Not given | W62: Active, not quotable (Rs 0) | X62: Category notes only (icu). No service-specific notes. | Y62: Y | Z62: Y | AA62: BIPAP-AUTO | AB62: Unpriced, No B2B, GST basis, Knowledge, Possible overlap | AC62: 0 | AD62: 1 | AE62: 1 | AF62: 1 | AG62: 1 | AH62: 1 | AI62: 0
A63: LAB-ABG | C63: Arterial Blood Gas Analysis (ABG Sample) | D63: lab | E63: SecondMedic (SM) | F63: SecondMedic (SM) | H63: test | I63: New item uses "test"; existing lab services use "unit". Align the wording before import. | K63: 1100 | M63: Not on the CRM rate card | N63: Not loaded | O63: 650 | P63: =IF(AND(ISNUMBER(J63),J63>0),ROUND(J63*Assumptions!$B$4,2),"") | Q63: =IF(AND(ISNUMBER(K63),ISNUMBER(O63)),IF(ROUND(K63*Assumptions!$B$4,2)=O63,"Equals 70%","Differs ("&TEXT(O63/K63,"0%")&" of B2C)"),"") -> Differs (59% of B2C) | R63: Not loaded. Draft B2B is unapproved. | T63: Exempt | U63: Not confirmed: CRM basis is empty; draft gives a GST rate, not whether prices include it | V63: Not given | W63: Not loaded | X63: No service yet. Category notes (lab) would apply after import. | Y63: N | Z63: Y | AB63: Unit, GST basis, Knowledge | AC63: 1 | AD63: 1 | AE63: 0 | AF63: 1 | AG63: 0 | AH63: 0 | AI63: 0
A64: LAB-B12 | C64: Vitamin B12 Cyanocobalamin | D64: lab | E64: SecondMedic (SM) | F64: SecondMedic (SM) | H64: test | I64: New item uses "test"; existing lab services use "unit". Align the wording before import. | K64: 950 | M64: Not on the CRM rate card | N64: Not loaded | O64: 520 | P64: =IF(AND(ISNUMBER(J64),J64>0),ROUND(J64*Assumptions!$B$4,2),"") | Q64: =IF(AND(ISNUMBER(K64),ISNUMBER(O64)),IF(ROUND(K64*Assumptions!$B$4,2)=O64,"Equals 70%","Differs ("&TEXT(O64/K64,"0%")&" of B2C)"),"") -> Differs (55% of B2C) | R64: Not loaded. Draft B2B is unapproved. | T64: Exempt | U64: Not confirmed: CRM basis is empty; draft gives a GST rate, not whether prices include it | V64: Not given | W64: Not loaded | X64: No service yet. Category notes (lab) would apply after import. | Y64: N | Z64: Y | AB64: Unit, GST basis, Knowledge | AC64: 1 | AD64: 1 | AE64: 0 | AF64: 1 | AG64: 0 | AH64: 0 | AI64: 0
A65: LAB-BLOODC | C65: Blood Culture & Sensitivity (Aerobic/Anaerobic) | D65: lab | E65: SecondMedic (SM) | F65: SecondMedic (SM) | H65: test | I65: New item uses "test"; existing lab services use "unit". Align the wording before import. | K65: 1400 | M65: Not on the CRM rate card | N65: Not loaded | O65: 850 | P65: =IF(AND(ISNUMBER(J65),J65>0),ROUND(J65*Assumptions!$B$4,2),"") | Q65: =IF(AND(ISNUMBER(K65),ISNUMBER(O65)),IF(ROUND(K65*Assumptions!$B$4,2)=O65,"Equals 70%","Differs ("&TEXT(O65/K65,"0%")&" of B2C)"),"") -> Differs (61% of B2C) | R65: Not loaded. Draft B2B is unapproved. | T65: Exempt | U65: Not confirmed: CRM basis is empty; draft gives a GST rate, not whether prices include it | V65: Not given | W65: Not loaded | X65: No service yet. Category notes (lab) would apply after import. | Y65: N | Z65: Y | AB65: Unit, GST basis, Knowledge | AC65: 1 | AD65: 1 | AE65: 0 | AF65: 1 | AG65: 0 | AH65: 0 | AI65: 0
A66: LAB-CBC | B66: Complete Blood Count | C66: Complete Blood Count (CBC) | D66: lab | E66: SecondMedic (SM) | F66: SecondMedic (SM) | G66: unit | H66: test | I66: Rate card "unit" vs draft "test". The importer refuses the row until one wording is chosen. | J66: 450 | K66: 450 | M66: Price written by migration 20261008100500 (proposal deck). No in-app approval record or named approver in the repo. | N66: None (0 buying rates in CRM) | O66: 250 | P66: =IF(AND(ISNUMBER(J66),J66>0),ROUND(J66*Assumptions!$B$4,2),"") -> 315 | Q66: =IF(AND(ISNUMBER(K66),ISNUMBER(O66)),IF(ROUND(K66*Assumptions!$B$4,2)=O66,"Equals 70%","Differs ("&TEXT(O66/K66,"0%")&" of B2C)"),"") -> Differs (56% of B2C) | R66: No buying rate. The 70% rule can derive one at import from the selling price. Draft B2B is unapproved. | S66: Not set | T66: Exempt | U66: Not confirmed: CRM basis is empty; draft gives a GST rate, not whether prices include it | V66: Not given | W66: Active, quotable | X66: Category notes only (lab). No service-specific notes. | Y66: Y | Z66: Y | AB66: Unit, No B2B, GST basis, Knowledge | AC66: 1 | AD66: 1 | AE66: 1 | AF66: 1 | AG66: 0 | AH66: 0 | AI66: 0
A67: LAB-CRP | C67: C-Reactive Protein (Quantitative CRP) | D67: lab | E67: SecondMedic (SM) | F67: SecondMedic (SM) | H67: test | I67: New item uses "test"; existing lab services use "unit". Align the wording before import. | K67: 550 | M67: Not on the CRM rate card | N67: Not loaded | O67: 300 | P67: =IF(AND(ISNUMBER(J67),J67>0),ROUND(J67*Assumptions!$B$4,2),"") | Q67: =IF(AND(ISNUMBER(K67),ISNUMBER(O67)),IF(ROUND(K67*Assumptions!$B$4,2)=O67,"Equals 70%","Differs ("&TEXT(O67/K67,"0%")&" of B2C)"),"") -> Differs (55% of B2C) | R67: Not loaded. Draft B2B is unapproved. | T67: Exempt | U67: Not confirmed: CRM basis is empty; draft gives a GST rate, not whether prices include it | V67: Not given | W67: Not loaded | X67: No service yet. Category notes (lab) would apply after import. | Y67: N | Z67: Y | AB67: Unit, GST basis, Knowledge | AC67: 1 | AD67: 1 | AE67: 0 | AF67: 1 | AG67: 0 | AH67: 0 | AI67: 0
A68: LAB-DDIMER | C68: D-Dimer Test | D68: lab | E68: SecondMedic (SM) | F68: SecondMedic (SM) | H68: test | I68: New item uses "test"; existing lab services use "unit". Align the wording before import. | K68: 1200 | M68: Not on the CRM rate card | N68: Not loaded | O68: 700 | P68: =IF(AND(ISNUMBER(J68),J68>0),ROUND(J68*Assumptions!$B$4,2),"") | Q68: =IF(AND(ISNUMBER(K68),ISNUMBER(O68)),IF(ROUND(K68*Assumptions!$B$4,2)=O68,"Equals 70%","Differs ("&TEXT(O68/K68,"0%")&" of B2C)"),"") -> Differs (58% of B2C) | R68: Not loaded. Draft B2B is unapproved. | T68: Exempt | U68: Not confirmed: CRM basis is empty; draft gives a GST rate, not whether prices include it | V68: Not given | W68: Not loaded | X68: No service yet. Category notes (lab) would apply after import. | Y68: N | Z68: Y | AB68: Unit, GST basis, Knowledge | AC68: 1 | AD68: 1 | AE68: 0 | AF68: 1 | AG68: 0 | AH68: 0 | AI68: 0
A69: LAB-ELECT | C69: Serum Electrolytes (Na, K, Cl) | D69: lab | E69: SecondMedic (SM) | F69: SecondMedic (SM) | H69: test | I69: New item uses "test"; existing lab services use "unit". Align the wording before import. | K69: 600 | M69: Not on the CRM rate card | N69: Not loaded | O69: 320 | P69: =IF(AND(ISNUMBER(J69),J69>0),ROUND(J69*Assumptions!$B$4,2),"") | Q69: =IF(AND(ISNUMBER(K69),ISNUMBER(O69)),IF(ROUND(K69*Assumptions!$B$4,2)=O69,"Equals 70%","Differs ("&TEXT(O69/K69,"0%")&" of B2C)"),"") -> Differs (53% of B2C) | R69: Not loaded. Draft B2B is unapproved. | T69: Exempt | U69: Not confirmed: CRM basis is empty; draft gives a GST rate, not whether prices include it | V69: Not given | W69: Not loaded | X69: No service yet. Category notes (lab) would apply after import. | Y69: N | Z69: Y | AB69: Unit, GST basis, Knowledge | AC69: 1 | AD69: 1 | AE69: 0 | AF69: 1 | AG69: 0 | AH69: 0 | AI69: 0
A70: LAB-HBA1C | B70: HbA1c | C70: HbA1c Glycated Hemoglobin | D70: lab | E70: SecondMedic (SM) | F70: SecondMedic (SM) | G70: unit | H70: test | I70: Rate card "unit" vs draft "test". The importer refuses the row until one wording is chosen. | J70: 600 | K70: 600 | M70: Price written by migration 20261008100500 (proposal deck). No in-app approval record or named approver in the repo. | N70: None (0 buying rates in CRM) | O70: 350 | P70: =IF(AND(ISNUMBER(J70),J70>0),ROUND(J70*Assumptions!$B$4,2),"") -> 420 | Q70: =IF(AND(ISNUMBER(K70),ISNUMBER(O70)),IF(ROUND(K70*Assumptions!$B$4,2)=O70,"Equals 70%","Differs ("&TEXT(O70/K70,"0%")&" of B2C)"),"") -> Differs (58% of B2C) | R70: No buying rate. The 70% rule can derive one at import from the selling price. Draft B2B is unapproved. | S70: Not set | T70: Exempt | U70: Not confirmed: CRM basis is empty; draft gives a GST rate, not whether prices include it | V70: Not given | W70: Active, quotable | X70: Category notes only (lab). No service-specific notes. | Y70: Y | Z70: Y | AB70: Unit, No B2B, GST basis, Knowledge | AC70: 1 | AD70: 1 | AE70: 1 | AF70: 1 | AG70: 0 | AH70: 0 | AI70: 0
A71: LAB-ICUPAN | C71: Post-ICU Transition Recovery Profile | D71: lab | E71: SecondMedic (SM) | F71: SecondMedic (SM) | H71: test | I71: New item uses "test"; existing lab services use "unit". Align the wording before import. | K71: 3500 | M71: Not on the CRM rate card | N71: Not loaded | O71: 2100 | P71: =IF(AND(ISNUMBER(J71),J71>0),ROUND(J71*Assumptions!$B$4,2),"") | Q71: =IF(AND(ISNUMBER(K71),ISNUMBER(O71)),IF(ROUND(K71*Assumptions!$B$4,2)=O71,"Equals 70%","Differs ("&TEXT(O71/K71,"0%")&" of B2C)"),"") -> Differs (60% of B2C) | R71: Not loaded. Draft B2B is unapproved. | T71: Exempt | U71: Not confirmed: CRM basis is empty; draft gives a GST rate, not whether prices include it | V71: Not given | W71: Not loaded | X71: No service yet. Category notes (lab) would apply after import. | Y71: N | Z71: Y | AB71: Unit, GST basis, Knowledge | AC71: 1 | AD71: 1 | AE71: 0 | AF71: 1 | AG71: 0 | AH71: 0 | AI71: 0
A72: LAB-KFT | B72: Kidney Function Test | C72: Kidney Function Test (KFT / RFT) | D72: lab | E72: SecondMedic (SM) | F72: SecondMedic (SM) | G72: unit | H72: test | I72: Rate card "unit" vs draft "test". The importer refuses the row until one wording is chosen. | J72: 800 | K72: 800 | M72: Price written by migration 20261008100500 (proposal deck). No in-app approval record or named approver in the repo. | N72: None (0 buying rates in CRM) | O72: 450 | P72: =IF(AND(ISNUMBER(J72),J72>0),ROUND(J72*Assumptions!$B$4,2),"") -> 560 | Q72: =IF(AND(ISNUMBER(K72),ISNUMBER(O72)),IF(ROUND(K72*Assumptions!$B$4,2)=O72,"Equals 70%","Differs ("&TEXT(O72/K72,"0%")&" of B2C)"),"") -> Differs (56% of B2C) | R72: No buying rate. The 70% rule can derive one at import from the selling price. Draft B2B is unapproved. | S72: Not set | T72: Exempt | U72: Not confirmed: CRM basis is empty; draft gives a GST rate, not whether prices include it | V72: Not given | W72: Active, quotable | X72: Category notes only (lab). No service-specific notes. | Y72: Y | Z72: Y | AB72: Unit, No B2B, GST basis, Knowledge | AC72: 1 | AD72: 1 | AE72: 1 | AF72: 1 | AG72: 0 | AH72: 0 | AI72: 0
A73: LAB-LFT | B73: Liver Function Test | C73: Liver Function Test (LFT) | D73: lab | E73: SecondMedic (SM) | F73: SecondMedic (SM) | G73: unit | H73: test | I73: Rate card "unit" vs draft "test". The importer refuses the row until one wording is chosen. | J73: 750 | K73: 750 | M73: Price written by migration 20261008100500 (proposal deck). No in-app approval record or named approver in the repo. | N73: None (0 buying rates in CRM) | O73: 420 | P73: =IF(AND(ISNUMBER(J73),J73>0),ROUND(J73*Assumptions!$B$4,2),"") -> 525 | Q73: =IF(AND(ISNUMBER(K73),ISNUMBER(O73)),IF(ROUND(K73*Assumptions!$B$4,2)=O73,"Equals 70%","Differs ("&TEXT(O73/K73,"0%")&" of B2C)"),"") -> Differs (56% of B2C) | R73: No buying rate. The 70% rule can derive one at import from the selling price. Draft B2B is unapproved. | S73: Not set | T73: Exempt | U73: Not confirmed: CRM basis is empty; draft gives a GST rate, not whether prices include it | V73: Not given | W73: Active, quotable | X73: Category notes only (lab). No service-specific notes. | Y73: Y | Z73: Y | AB73: Unit, No B2B, GST basis, Knowledge | AC73: 1 | AD73: 1 | AE73: 1 | AF73: 1 | AG73: 0 | AH73: 0 | AI73: 0
A74: LAB-LIPID | B74: Lipid Profile | C74: Lipid Profile (Cholesterol & Triglycerides) | D74: lab | E74: SecondMedic (SM) | F74: SecondMedic (SM) | G74: unit | H74: test | I74: Rate card "unit" vs draft "test". The importer refuses the row until one wording is chosen. | J74: 700 | K74: 700 | M74: Price written by migration 20261008100500 (proposal deck). No in-app approval record or named approver in the repo. | N74: None (0 buying rates in CRM) | O74: 380 | P74: =IF(AND(ISNUMBER(J74),J74>0),ROUND(J74*Assumptions!$B$4,2),"") -> 490 | Q74: =IF(AND(ISNUMBER(K74),ISNUMBER(O74)),IF(ROUND(K74*Assumptions!$B$4,2)=O74,"Equals 70%","Differs ("&TEXT(O74/K74,"0%")&" of B2C)"),"") -> Differs (54% of B2C) | R74: No buying rate. The 70% rule can derive one at import from the selling price. Draft B2B is unapproved. | S74: Not set | T74: Exempt | U74: Not confirmed: CRM basis is empty; draft gives a GST rate, not whether prices include it | V74: Not given | W74: Active, quotable | X74: Category notes only (lab). No service-specific notes. | Y74: Y | Z74: Y | AB74: Unit, No B2B, GST basis, Knowledge | AC74: 1 | AD74: 1 | AE74: 1 | AF74: 1 | AG74: 0 | AH74: 0 | AI74: 0
A75: LAB-PANEL | B75: Senior Citizen Health Panel | C75: Senior Citizen Comprehensive Health Panel | D75: lab | E75: SecondMedic (SM) | F75: SecondMedic (SM) | G75: unit | H75: test | I75: Rate card "unit" vs draft "test". The importer refuses the row until one wording is chosen. | J75: 2800 | K75: 2800 | M75: Price written by migration 20261008100500 (proposal deck). No in-app approval record or named approver in the repo. | N75: None (0 buying rates in CRM) | O75: 1600 | P75: =IF(AND(ISNUMBER(J75),J75>0),ROUND(J75*Assumptions!$B$4,2),"") -> 1960 | Q75: =IF(AND(ISNUMBER(K75),ISNUMBER(O75)),IF(ROUND(K75*Assumptions!$B$4,2)=O75,"Equals 70%","Differs ("&TEXT(O75/K75,"0%")&" of B2C)"),"") -> Differs (57% of B2C) | R75: No buying rate. The 70% rule can derive one at import from the selling price. Draft B2B is unapproved. | S75: Not set | T75: Exempt | U75: Not confirmed: CRM basis is empty; draft gives a GST rate, not whether prices include it | V75: Not given | W75: Active, quotable | X75: Category notes only (lab). No service-specific notes. | Y75: Y | Z75: Y | AB75: Unit, No B2B, GST basis, Knowledge | AC75: 1 | AD75: 1 | AE75: 1 | AF75: 1 | AG75: 0 | AH75: 0 | AI75: 0
A76: LAB-PROCAL | C76: Procalcitonin (PCT) Sepsis Marker | D76: lab | E76: SecondMedic (SM) | F76: SecondMedic (SM) | H76: test | I76: New item uses "test"; existing lab services use "unit". Align the wording before import. | K76: 2500 | M76: Not on the CRM rate card | N76: Not loaded | O76: 1600 | P76: =IF(AND(ISNUMBER(J76),J76>0),ROUND(J76*Assumptions!$B$4,2),"") | Q76: =IF(AND(ISNUMBER(K76),ISNUMBER(O76)),IF(ROUND(K76*Assumptions!$B$4,2)=O76,"Equals 70%","Differs ("&TEXT(O76/K76,"0%")&" of B2C)"),"") -> Differs (64% of B2C) | R76: Not loaded. Draft B2B is unapproved. | T76: Exempt | U76: Not confirmed: CRM basis is empty; draft gives a GST rate, not whether prices include it | V76: Not given | W76: Not loaded | X76: No service yet. Category notes (lab) would apply after import. | Y76: N | Z76: Y | AB76: Unit, GST basis, Knowledge | AC76: 1 | AD76: 1 | AE76: 0 | AF76: 1 | AG76: 0 | AH76: 0 | AI76: 0
A77: LAB-PTINR | C77: Prothrombin Time with INR (PT-INR) | D77: lab | E77: SecondMedic (SM) | F77: SecondMedic (SM) | H77: test | I77: New item uses "test"; existing lab services use "unit". Align the wording before import. | K77: 450 | M77: Not on the CRM rate card | N77: Not loaded | O77: 250 | P77: =IF(AND(ISNUMBER(J77),J77>0),ROUND(J77*Assumptions!$B$4,2),"") | Q77: =IF(AND(ISNUMBER(K77),ISNUMBER(O77)),IF(ROUND(K77*Assumptions!$B$4,2)=O77,"Equals 70%","Differs ("&TEXT(O77/K77,"0%")&" of B2C)"),"") -> Differs (56% of B2C) | R77: Not loaded. Draft B2B is unapproved. | T77: Exempt | U77: Not confirmed: CRM basis is empty; draft gives a GST rate, not whether prices include it | V77: Not given | W77: Not loaded | X77: No service yet. Category notes (lab) would apply after import. | Y77: N | Z77: Y | AB77: Unit, GST basis, Knowledge | AC77: 1 | AD77: 1 | AE77: 0 | AF77: 1 | AG77: 0 | AH77: 0 | AI77: 0
A78: LAB-THY | B78: Thyroid Profile (T3, T4, TSH) | C78: Thyroid Panel (Total T3, T4, TSH) | D78: lab | E78: SecondMedic (SM) | F78: SecondMedic (SM) | G78: unit | H78: test | I78: Rate card "unit" vs draft "test". The importer refuses the row until one wording is chosen. | J78: 650 | K78: 650 | M78: Price written by migration 20261008100500 (proposal deck). No in-app approval record or named approver in the repo. | N78: None (0 buying rates in CRM) | O78: 350 | P78: =IF(AND(ISNUMBER(J78),J78>0),ROUND(J78*Assumptions!$B$4,2),"") -> 455 | Q78: =IF(AND(ISNUMBER(K78),ISNUMBER(O78)),IF(ROUND(K78*Assumptions!$B$4,2)=O78,"Equals 70%","Differs ("&TEXT(O78/K78,"0%")&" of B2C)"),"") -> Differs (54% of B2C) | R78: No buying rate. The 70% rule can derive one at import from the selling price. Draft B2B is unapproved. | S78: Not set | T78: Exempt | U78: Not confirmed: CRM basis is empty; draft gives a GST rate, not whether prices include it | V78: Not given | W78: Active, quotable | X78: Category notes only (lab). No service-specific notes. | Y78: Y | Z78: Y | AB78: Unit, No B2B, GST basis, Knowledge | AC78: 1 | AD78: 1 | AE78: 1 | AF78: 1 | AG78: 0 | AH78: 0 | AI78: 0
A79: LAB-URINE | C79: Urine Routine & Microscopic Examination | D79: lab | E79: SecondMedic (SM) | F79: SecondMedic (SM) | H79: test | I79: New item uses "test"; existing lab services use "unit". Align the wording before import. | K79: 300 | M79: Not on the CRM rate card | N79: Not loaded | O79: 150 | P79: =IF(AND(ISNUMBER(J79),J79>0),ROUND(J79*Assumptions!$B$4,2),"") | Q79: =IF(AND(ISNUMBER(K79),ISNUMBER(O79)),IF(ROUND(K79*Assumptions!$B$4,2)=O79,"Equals 70%","Differs ("&TEXT(O79/K79,"0%")&" of B2C)"),"") -> Differs (50% of B2C) | R79: Not loaded. Draft B2B is unapproved. | T79: Exempt | U79: Not confirmed: CRM basis is empty; draft gives a GST rate, not whether prices include it | V79: Not given | W79: Not loaded | X79: No service yet. Category notes (lab) would apply after import. | Y79: N | Z79: Y | AB79: Unit, GST basis, Knowledge | AC79: 1 | AD79: 1 | AE79: 0 | AF79: 1 | AG79: 0 | AH79: 0 | AI79: 0
A80: LAB-URINEC | C80: Urine Culture & Antibiotic Sensitivity | D80: lab | E80: SecondMedic (SM) | F80: SecondMedic (SM) | H80: test | I80: New item uses "test"; existing lab services use "unit". Align the wording before import. | K80: 900 | M80: Not on the CRM rate card | N80: Not loaded | O80: 500 | P80: =IF(AND(ISNUMBER(J80),J80>0),ROUND(J80*Assumptions!$B$4,2),"") | Q80: =IF(AND(ISNUMBER(K80),ISNUMBER(O80)),IF(ROUND(K80*Assumptions!$B$4,2)=O80,"Equals 70%","Differs ("&TEXT(O80/K80,"0%")&" of B2C)"),"") -> Differs (56% of B2C) | R80: Not loaded. Draft B2B is unapproved. | T80: Exempt | U80: Not confirmed: CRM basis is empty; draft gives a GST rate, not whether prices include it | V80: Not given | W80: Not loaded | X80: No service yet. Category notes (lab) would apply after import. | Y80: N | Z80: Y | AB80: Unit, GST basis, Knowledge | AC80: 1 | AD80: 1 | AE80: 0 | AF80: 1 | AG80: 0 | AH80: 0 | AI80: 0
A81: LAB-VITD | C81: Vitamin D 25-Hydroxy | D81: lab | E81: SecondMedic (SM) | F81: SecondMedic (SM) | H81: test | I81: New item uses "test"; existing lab services use "unit". Align the wording before import. | K81: 1200 | M81: Not on the CRM rate card | N81: Not loaded | O81: 650 | P81: =IF(AND(ISNUMBER(J81),J81>0),ROUND(J81*Assumptions!$B$4,2),"") | Q81: =IF(AND(ISNUMBER(K81),ISNUMBER(O81)),IF(ROUND(K81*Assumptions!$B$4,2)=O81,"Equals 70%","Differs ("&TEXT(O81/K81,"0%")&" of B2C)"),"") -> Differs (54% of B2C) | R81: Not loaded. Draft B2B is unapproved. | T81: Exempt | U81: Not confirmed: CRM basis is empty; draft gives a GST rate, not whether prices include it | V81: Not given | W81: Not loaded | X81: No service yet. Category notes (lab) would apply after import. | Y81: N | Z81: Y | AB81: Unit, GST basis, Knowledge | AC81: 1 | AD81: 1 | AE81: 0 | AF81: 1 | AG81: 0 | AH81: 0 | AI81: 0
A82: NURS-BEDSOR | C82: Bed Sore Debridement & Advanced Dressing | D82: nursing | E82: Book My Medicare (BMM) | F82: Book My Medicare (BMM) | H82: session | I82: Only one source; unit as given | K82: 1200 | M82: Not on the CRM rate card | N82: Not loaded | O82: 800 | P82: =IF(AND(ISNUMBER(J82),J82>0),ROUND(J82*Assumptions!$B$4,2),"") | Q82: =IF(AND(ISNUMBER(K82),ISNUMBER(O82)),IF(ROUND(K82*Assumptions!$B$4,2)=O82,"Equals 70%","Differs ("&TEXT(O82/K82,"0%")&" of B2C)"),"") -> Differs (67% of B2C) | R82: Not loaded. Draft B2B is unapproved. | T82: Exempt | U82: Not confirmed: CRM basis is empty; draft gives a GST rate, not whether prices include it | V82: Not given | W82: Not loaded | X82: No service yet. Category notes (nursing) would apply after import. | Y82: N | Z82: Y | AB82: GST basis, Knowledge | AC82: 0 | AD82: 1 | AE82: 0 | AF82: 1 | AG82: 0 | AH82: 0 | AI82: 0
A83: NURS-CATH | C83: Urinary Catheterization (Foley Insertion/Change) | D83: nursing | E83: Book My Medicare (BMM) | F83: Book My Medicare (BMM) | H83: session | I83: Only one source; unit as given | K83: 900 | M83: Not on the CRM rate card | N83: Not loaded | O83: 600 | P83: =IF(AND(ISNUMBER(J83),J83>0),ROUND(J83*Assumptions!$B$4,2),"") | Q83: =IF(AND(ISNUMBER(K83),ISNUMBER(O83)),IF(ROUND(K83*Assumptions!$B$4,2)=O83,"Equals 70%","Differs ("&TEXT(O83/K83,"0%")&" of B2C)"),"") -> Differs (67% of B2C) | R83: Not loaded. Draft B2B is unapproved. | T83: Exempt | U83: Not confirmed: CRM basis is empty; draft gives a GST rate, not whether prices include it | V83: Not given | W83: Not loaded | X83: No service yet. Category notes (nursing) would apply after import. | Y83: N | Z83: Y | AB83: GST basis, Knowledge | AC83: 0 | AD83: 1 | AE83: 0 | AF83: 1 | AG83: 0 | AH83: 0 | AI83: 0
A84: NURS-DRESS | C84: Surgical Wound Dressing & Care (Sterile) | D84: nursing | E84: Book My Medicare (BMM) | F84: Book My Medicare (BMM) | H84: session | I84: Only one source; unit as given | K84: 850 | M84: Not on the CRM rate card | N84: Not loaded | O84: 550 | P84: =IF(AND(ISNUMBER(J84),J84>0),ROUND(J84*Assumptions!$B$4,2),"") | Q84: =IF(AND(ISNUMBER(K84),ISNUMBER(O84)),IF(ROUND(K84*Assumptions!$B$4,2)=O84,"Equals 70%","Differs ("&TEXT(O84/K84,"0%")&" of B2C)"),"") -> Differs (65% of B2C) | R84: Not loaded. Draft B2B is unapproved. | T84: Exempt | U84: Not confirmed: CRM basis is empty; draft gives a GST rate, not whether prices include it | V84: Not given | W84: Not loaded | X84: No service yet. Category notes (nursing) would apply after import. | Y84: N | Z84: Y | AB84: GST basis, Knowledge | AC84: 0 | AD84: 1 | AE84: 0 | AF84: 1 | AG84: 0 | AH84: 0 | AI84: 0
A85: NURS-HOME | B85: Nursing care at home | D85: nursing | E85: Book My Medicare (BMM) | G85: shift | I85: Only one source; unit as given | J85: 0 | M85: Not priced: Rs 0 placeholder, agents see "quote required" | N85: None (0 buying rates in CRM) | P85: =IF(AND(ISNUMBER(J85),J85>0),ROUND(J85*Assumptions!$B$4,2),"") | Q85: =IF(AND(ISNUMBER(K85),ISNUMBER(O85)),IF(ROUND(K85*Assumptions!$B$4,2)=O85,"Equals 70%","Differs ("&TEXT(O85/K85,"0%")&" of B2C)"),"") | R85: No buying rate, and none derivable: no selling price. | S85: Not set | U85: Not confirmed: CRM basis is empty | V85: Not given | W85: Active, not quotable (Rs 0) | X85: Category notes only (nursing). No service-specific notes. | Y85: Y | Z85: N | AA85: NURSE-12H, NURSE-24H, NURS-VISIT | AB85: Unpriced, No B2B, GST basis, Knowledge, Possible overlap | AC85: 0 | AD85: 1 | AE85: 1 | AF85: 1 | AG85: 1 | AH85: 1 | AI85: 0
A86: NURS-IVINF | C86: IV Cannula Insertion & Infusion Administration | D86: nursing | E86: Book My Medicare (BMM) | F86: Book My Medicare (BMM) | H86: session | I86: Only one source; unit as given | K86: 750 | M86: Not on the CRM rate card | N86: Not loaded | O86: 500 | P86: =IF(AND(ISNUMBER(J86),J86>0),ROUND(J86*Assumptions!$B$4,2),"") | Q86: =IF(AND(ISNUMBER(K86),ISNUMBER(O86)),IF(ROUND(K86*Assumptions!$B$4,2)=O86,"Equals 70%","Differs ("&TEXT(O86/K86,"0%")&" of B2C)"),"") -> Differs (67% of B2C) | R86: Not loaded. Draft B2B is unapproved. | T86: Exempt | U86: Not confirmed: CRM basis is empty; draft gives a GST rate, not whether prices include it | V86: Not given | W86: Not loaded | X86: No service yet. Category notes (nursing) would apply after import. | Y86: N | Z86: Y | AB86: GST basis, Knowledge | AC86: 0 | AD86: 1 | AE86: 0 | AF86: 1 | AG86: 0 | AH86: 0 | AI86: 0
A87: NURS-PICCL | C87: PICC Line / Central Line Dressing & Heparin Flush | D87: nursing | E87: Book My Medicare (BMM) | F87: Book My Medicare (BMM) | H87: session | I87: Only one source; unit as given | K87: 1400 | M87: Not on the CRM rate card | N87: Not loaded | O87: 950 | P87: =IF(AND(ISNUMBER(J87),J87>0),ROUND(J87*Assumptions!$B$4,2),"") | Q87: =IF(AND(ISNUMBER(K87),ISNUMBER(O87)),IF(ROUND(K87*Assumptions!$B$4,2)=O87,"Equals 70%","Differs ("&TEXT(O87/K87,"0%")&" of B2C)"),"") -> Differs (68% of B2C) | R87: Not loaded. Draft B2B is unapproved. | T87: Exempt | U87: Not confirmed: CRM basis is empty; draft gives a GST rate, not whether prices include it | V87: Not given | W87: Not loaded | X87: No service yet. Category notes (nursing) would apply after import. | Y87: N | Z87: Y | AB87: GST basis, Knowledge | AC87: 0 | AD87: 1 | AE87: 0 | AF87: 1 | AG87: 0 | AH87: 0 | AI87: 0
A88: NURS-RYLE | C88: Nasogastric (Ryle's) Tube Insertion & Care | D88: nursing | E88: Book My Medicare (BMM) | F88: Book My Medicare (BMM) | H88: session | I88: Only one source; unit as given | K88: 950 | M88: Not on the CRM rate card | N88: Not loaded | O88: 650 | P88: =IF(AND(ISNUMBER(J88),J88>0),ROUND(J88*Assumptions!$B$4,2),"") | Q88: =IF(AND(ISNUMBER(K88),ISNUMBER(O88)),IF(ROUND(K88*Assumptions!$B$4,2)=O88,"Equals 70%","Differs ("&TEXT(O88/K88,"0%")&" of B2C)"),"") -> Differs (68% of B2C) | R88: Not loaded. Draft B2B is unapproved. | T88: Exempt | U88: Not confirmed: CRM basis is empty; draft gives a GST rate, not whether prices include it | V88: Not given | W88: Not loaded | X88: No service yet. Category notes (nursing) would apply after import. | Y88: N | Z88: Y | AB88: GST basis, Knowledge | AC88: 0 | AD88: 1 | AE88: 0 | AF88: 1 | AG88: 0 | AH88: 0 | AI88: 0
A89: NURS-STOMA | C89: Colostomy / Stoma Bag Care & Training | D89: nursing | E89: Book My Medicare (BMM) | F89: Book My Medicare (BMM) | H89: session | I89: Only one source; unit as given | K89: 1000 | M89: Not on the CRM rate card | N89: Not loaded | O89: 680 | P89: =IF(AND(ISNUMBER(J89),J89>0),ROUND(J89*Assumptions!$B$4,2),"") | Q89: =IF(AND(ISNUMBER(K89),ISNUMBER(O89)),IF(ROUND(K89*Assumptions!$B$4,2)=O89,"Equals 70%","Differs ("&TEXT(O89/K89,"0%")&" of B2C)"),"") -> Differs (68% of B2C) | R89: Not loaded. Draft B2B is unapproved. | T89: Exempt | U89: Not confirmed: CRM basis is empty; draft gives a GST rate, not whether prices include it | V89: Not given | W89: Not loaded | X89: No service yet. Category notes (nursing) would apply after import. | Y89: N | Z89: Y | AB89: GST basis, Knowledge | AC89: 0 | AD89: 1 | AE89: 0 | AF89: 1 | AG89: 0 | AH89: 0 | AI89: 0
A90: NURS-TRACH | C90: Tracheostomy Care & Tube Suctioning | D90: nursing | E90: Book My Medicare (BMM) | F90: Book My Medicare (BMM) | H90: session | I90: Only one source; unit as given | K90: 1100 | M90: Not on the CRM rate card | N90: Not loaded | O90: 750 | P90: =IF(AND(ISNUMBER(J90),J90>0),ROUND(J90*Assumptions!$B$4,2),"") | Q90: =IF(AND(ISNUMBER(K90),ISNUMBER(O90)),IF(ROUND(K90*Assumptions!$B$4,2)=O90,"Equals 70%","Differs ("&TEXT(O90/K90,"0%")&" of B2C)"),"") -> Differs (68% of B2C) | R90: Not loaded. Draft B2B is unapproved. | T90: Exempt | U90: Not confirmed: CRM basis is empty; draft gives a GST rate, not whether prices include it | V90: Not given | W90: Not loaded | X90: No service yet. Category notes (nursing) would apply after import. | Y90: N | Z90: Y | AB90: GST basis, Knowledge | AC90: 0 | AD90: 1 | AE90: 0 | AF90: 1 | AG90: 0 | AH90: 0 | AI90: 0
A91: NURS-VISIT | C91: Nurse Short Procedure Home Visit (< 1 hr) | D91: nursing | E91: Book My Medicare (BMM) | F91: Book My Medicare (BMM) | H91: session | I91: Only one source; unit as given | K91: 650 | M91: Not on the CRM rate card | N91: Not loaded | O91: 450 | P91: =IF(AND(ISNUMBER(J91),J91>0),ROUND(J91*Assumptions!$B$4,2),"") | Q91: =IF(AND(ISNUMBER(K91),ISNUMBER(O91)),IF(ROUND(K91*Assumptions!$B$4,2)=O91,"Equals 70%","Differs ("&TEXT(O91/K91,"0%")&" of B2C)"),"") -> Differs (69% of B2C) | R91: Not loaded. Draft B2B is unapproved. | T91: Exempt | U91: Not confirmed: CRM basis is empty; draft gives a GST rate, not whether prices include it | V91: Not given | W91: Not loaded | X91: No service yet. Category notes (nursing) would apply after import. | Y91: N | Z91: Y | AA91: NURS-HOME | AB91: GST basis, Knowledge, Possible overlap | AC91: 0 | AD91: 1 | AE91: 0 | AF91: 1 | AG91: 1 | AH91: 0 | AI91: 0
A92: NURSE-12H | B92: Nurse, 12-hour shift | C92: Qualified Nurse (12-Hour Shift: Day or Night) | D92: nursing | E92: Book My Medicare (BMM) | F92: Book My Medicare (BMM) | G92: shift | H92: shift | I92: 12-hour shift. Confirm "shift" means 12 hours for every provider. | J92: 0 | K92: 2000 | M92: Not priced: Rs 0 placeholder, agents see "quote required" | N92: None (0 buying rates in CRM) | O92: 1500 | P92: =IF(AND(ISNUMBER(J92),J92>0),ROUND(J92*Assumptions!$B$4,2),"") | Q92: =IF(AND(ISNUMBER(K92),ISNUMBER(O92)),IF(ROUND(K92*Assumptions!$B$4,2)=O92,"Equals 70%","Differs ("&TEXT(O92/K92,"0%")&" of B2C)"),"") -> Differs (75% of B2C) | R92: No buying rate, and none derivable: no selling price. Draft B2B is unapproved. | S92: Not set | T92: Exempt | U92: Not confirmed: CRM basis is empty; draft gives a GST rate, not whether prices include it | V92: Not given | W92: Active, not quotable (Rs 0) | X92: Category notes only (nursing). No service-specific notes. | Y92: Y | Z92: Y | AA92: NURS-HOME | AB92: Unpriced, No B2B, GST basis, Knowledge, Possible overlap | AC92: 0 | AD92: 1 | AE92: 1 | AF92: 1 | AG92: 1 | AH92: 1 | AI92: 0
A93: NURSE-24H | C93: Qualified Nurse (24-Hour Residential Care) | D93: nursing | E93: Book My Medicare (BMM) | F93: Book My Medicare (BMM) | H93: shift | I93: 24-hour cover labelled "shift", the same unit as the 12-hour services. Needs its own unit (e.g. "24 hours") before import. | K93: 3800 | M93: Not on the CRM rate card | N93: Not loaded | O93: 2850 | P93: =IF(AND(ISNUMBER(J93),J93>0),ROUND(J93*Assumptions!$B$4,2),"") | Q93: =IF(AND(ISNUMBER(K93),ISNUMBER(O93)),IF(ROUND(K93*Assumptions!$B$4,2)=O93,"Equals 70%","Differs ("&TEXT(O93/K93,"0%")&" of B2C)"),"") -> Differs (75% of B2C) | R93: Not loaded. Draft B2B is unapproved. | T93: Exempt | U93: Not confirmed: CRM basis is empty; draft gives a GST rate, not whether prices include it | V93: Not given | W93: Not loaded | X93: No service yet. Category notes (nursing) would apply after import. | Y93: N | Z93: Y | AA93: NURS-HOME | AB93: Unit, GST basis, Knowledge, Possible overlap | AC93: 1 | AD93: 1 | AE93: 0 | AF93: 1 | AG93: 1 | AH93: 0 | AI93: 0
A94: NURSE-ICU12 | C94: Critical Care / ICU-Trained Nurse (12-Hour) | D94: nursing | E94: Book My Medicare (BMM) | F94: Book My Medicare (BMM) | H94: shift | I94: 12-hour shift. Confirm "shift" means 12 hours for every provider. | K94: 2500 | M94: Not on the CRM rate card | N94: Not loaded | O94: 1900 | P94: =IF(AND(ISNUMBER(J94),J94>0),ROUND(J94*Assumptions!$B$4,2),"") | Q94: =IF(AND(ISNUMBER(K94),ISNUMBER(O94)),IF(ROUND(K94*Assumptions!$B$4,2)=O94,"Equals 70%","Differs ("&TEXT(O94/K94,"0%")&" of B2C)"),"") -> Differs (76% of B2C) | R94: Not loaded. Draft B2B is unapproved. | T94: Exempt | U94: Not confirmed: CRM basis is empty; draft gives a GST rate, not whether prices include it | V94: Not given | W94: Not loaded | X94: No service yet. Category notes (nursing) would apply after import. | Y94: N | Z94: Y | AB94: GST basis, Knowledge | AC94: 0 | AD94: 1 | AE94: 0 | AF94: 1 | AG94: 0 | AH94: 0 | AI94: 0
A95: NURSE-ICU24 | C95: Critical Care / ICU-Trained Nurse (24-Hour) | D95: nursing | E95: Book My Medicare (BMM) | F95: Book My Medicare (BMM) | H95: shift | I95: 24-hour cover labelled "shift", the same unit as the 12-hour services. Needs its own unit (e.g. "24 hours") before import. | K95: 4800 | M95: Not on the CRM rate card | N95: Not loaded | O95: 3600 | P95: =IF(AND(ISNUMBER(J95),J95>0),ROUND(J95*Assumptions!$B$4,2),"") | Q95: =IF(AND(ISNUMBER(K95),ISNUMBER(O95)),IF(ROUND(K95*Assumptions!$B$4,2)=O95,"Equals 70%","Differs ("&TEXT(O95/K95,"0%")&" of B2C)"),"") -> Differs (75% of B2C) | R95: Not loaded. Draft B2B is unapproved. | T95: Exempt | U95: Not confirmed: CRM basis is empty; draft gives a GST rate, not whether prices include it | V95: Not given | W95: Not loaded | X95: No service yet. Category notes (nursing) would apply after import. | Y95: N | Z95: Y | AB95: Unit, GST basis, Knowledge | AC95: 1 | AD95: 1 | AE95: 0 | AF95: 1 | AG95: 0 | AH95: 0 | AI95: 0
A96: PHYSIO-GEN | C96: General Physiotherapy Session (Mobility/Gait) | D96: physio | E96: Book My Medicare (BMM) | F96: Book My Medicare (BMM) | H96: session | I96: Only one source; unit as given | K96: 900 | M96: Not on the CRM rate card | N96: Not loaded | O96: 650 | P96: =IF(AND(ISNUMBER(J96),J96>0),ROUND(J96*Assumptions!$B$4,2),"") | Q96: =IF(AND(ISNUMBER(K96),ISNUMBER(O96)),IF(ROUND(K96*Assumptions!$B$4,2)=O96,"Equals 70%","Differs ("&TEXT(O96/K96,"0%")&" of B2C)"),"") -> Differs (72% of B2C) | R96: Not loaded. Draft B2B is unapproved. | T96: Exempt | U96: Not confirmed: CRM basis is empty; draft gives a GST rate, not whether prices include it | V96: Not given | W96: Not loaded | X96: No service yet. Category notes (physio) would apply after import. | Y96: N | Z96: Y | AA96: PHYSIO-HOME | AB96: GST basis, Knowledge, Possible overlap | AC96: 0 | AD96: 1 | AE96: 0 | AF96: 1 | AG96: 1 | AH96: 0 | AI96: 0
A97: PHYSIO-HOME | B97: Physiotherapy at home | D97: physio | E97: Book My Medicare (BMM) | G97: session | I97: Only one source; unit as given | J97: 0 | M97: Not priced: Rs 0 placeholder, agents see "quote required" | N97: None (0 buying rates in CRM) | P97: =IF(AND(ISNUMBER(J97),J97>0),ROUND(J97*Assumptions!$B$4,2),"") | Q97: =IF(AND(ISNUMBER(K97),ISNUMBER(O97)),IF(ROUND(K97*Assumptions!$B$4,2)=O97,"Equals 70%","Differs ("&TEXT(O97/K97,"0%")&" of B2C)"),"") | R97: No buying rate, and none derivable: no selling price. | S97: Not set | U97: Not confirmed: CRM basis is empty | V97: Not given | W97: Active, not quotable (Rs 0) | X97: Category notes only (physio). No service-specific notes. | Y97: Y | Z97: N | AA97: PHYSIO-GEN, PHYSIO-NEU, PHYSIO-ORT, PHYSIO-RES | AB97: Unpriced, No B2B, GST basis, Knowledge, Possible overlap | AC97: 0 | AD97: 1 | AE97: 1 | AF97: 1 | AG97: 1 | AH97: 1 | AI97: 0
A98: PHYSIO-NEU | C98: Neuro-Physiotherapy (Stroke / Paralysis Rehab) | D98: physio | E98: Book My Medicare (BMM) | F98: Book My Medicare (BMM) | H98: session | I98: Only one source; unit as given | K98: 1200 | M98: Not on the CRM rate card | N98: Not loaded | O98: 850 | P98: =IF(AND(ISNUMBER(J98),J98>0),ROUND(J98*Assumptions!$B$4,2),"") | Q98: =IF(AND(ISNUMBER(K98),ISNUMBER(O98)),IF(ROUND(K98*Assumptions!$B$4,2)=O98,"Equals 70%","Differs ("&TEXT(O98/K98,"0%")&" of B2C)"),"") -> Differs (71% of B2C) | R98: Not loaded. Draft B2B is unapproved. | T98: Exempt | U98: Not confirmed: CRM basis is empty; draft gives a GST rate, not whether prices include it | V98: Not given | W98: Not loaded | X98: No service yet. Category notes (physio) would apply after import. | Y98: N | Z98: Y | AA98: PHYSIO-HOME | AB98: GST basis, Knowledge, Possible overlap | AC98: 0 | AD98: 1 | AE98: 0 | AF98: 1 | AG98: 1 | AH98: 0 | AI98: 0
A99: PHYSIO-ORT | C99: Orthopedic / Post-Surgical Rehab Session | D99: physio | E99: Book My Medicare (BMM) | F99: Book My Medicare (BMM) | H99: session | I99: Only one source; unit as given | K99: 1000 | M99: Not on the CRM rate card | N99: Not loaded | O99: 720 | P99: =IF(AND(ISNUMBER(J99),J99>0),ROUND(J99*Assumptions!$B$4,2),"") | Q99: =IF(AND(ISNUMBER(K99),ISNUMBER(O99)),IF(ROUND(K99*Assumptions!$B$4,2)=O99,"Equals 70%","Differs ("&TEXT(O99/K99,"0%")&" of B2C)"),"") -> Differs (72% of B2C) | R99: Not loaded. Draft B2B is unapproved. | T99: Exempt | U99: Not confirmed: CRM basis is empty; draft gives a GST rate, not whether prices include it | V99: Not given | W99: Not loaded | X99: No service yet. Category notes (physio) would apply after import. | Y99: N | Z99: Y | AA99: PHYSIO-HOME | AB99: GST basis, Knowledge, Possible overlap | AC99: 0 | AD99: 1 | AE99: 0 | AF99: 1 | AG99: 1 | AH99: 0 | AI99: 0
A100: PHYSIO-RES | C100: Cardio-Pulmonary / Chest Physiotherapy | D100: physio | E100: Book My Medicare (BMM) | F100: Book My Medicare (BMM) | H100: session | I100: Only one source; unit as given | K100: 1100 | M100: Not on the CRM rate card | N100: Not loaded | O100: 780 | P100: =IF(AND(ISNUMBER(J100),J100>0),ROUND(J100*Assumptions!$B$4,2),"") | Q100: =IF(AND(ISNUMBER(K100),ISNUMBER(O100)),IF(ROUND(K100*Assumptions!$B$4,2)=O100,"Equals 70%","Differs ("&TEXT(O100/K100,"0%")&" of B2C)"),"") -> Differs (71% of B2C) | R100: Not loaded. Draft B2B is unapproved. | T100: Exempt | U100: Not confirmed: CRM basis is empty; draft gives a GST rate, not whether prices include it | V100: Not given | W100: Not loaded | X100: No service yet. Category notes (physio) would apply after import. | Y100: N | Z100: Y | AA100: PHYSIO-HOME | AB100: GST basis, Knowledge, Possible overlap | AC100: 0 | AD100: 1 | AE100: 0 | AF100: 1 | AG100: 1 | AH100: 0 | AI100: 0
A101: SPEECH-TH | C101: Speech & Swallowing Therapy Session | D101: physio | E101: Book My Medicare (BMM) | F101: Book My Medicare (BMM) | H101: session | I101: Only one source; unit as given | K101: 1300 | M101: Not on the CRM rate card | N101: Not loaded | O101: 920 | P101: =IF(AND(ISNUMBER(J101),J101>0),ROUND(J101*Assumptions!$B$4,2),"") | Q101: =IF(AND(ISNUMBER(K101),ISNUMBER(O101)),IF(ROUND(K101*Assumptions!$B$4,2)=O101,"Equals 70%","Differs ("&TEXT(O101/K101,"0%")&" of B2C)"),"") -> Differs (71% of B2C) | R101: Not loaded. Draft B2B is unapproved. | T101: Exempt | U101: Not confirmed: CRM basis is empty; draft gives a GST rate, not whether prices include it | V101: Not given | W101: Not loaded | X101: No service yet. Category notes (physio) would apply after import. | Y101: N | Z101: Y | AB101: GST basis, Knowledge | AC101: 0 | AD101: 1 | AE101: 0 | AF101: 1 | AG101: 0 | AH101: 0 | AI101: 0
A102: VISIT-STD | B102: Home visit charge | C102: Home Assessment & Care Coordinator Visit | D102: visit | E102: SecondMedic (SM) | F102: SecondMedic (SM) | G102: unit | H102: visit | I102: Rate card "unit" vs draft "visit". The importer refuses the row until one wording is chosen. | J102: 150 | K102: 150 | M102: Price written by migration 20261008100500 (proposal deck). No in-app approval record or named approver in the repo. | N102: None (0 buying rates in CRM) | O102: 100 | P102: =IF(AND(ISNUMBER(J102),J102>0),ROUND(J102*Assumptions!$B$4,2),"") -> 105 | Q102: =IF(AND(ISNUMBER(K102),ISNUMBER(O102)),IF(ROUND(K102*Assumptions!$B$4,2)=O102,"Equals 70%","Differs ("&TEXT(O102/K102,"0%")&" of B2C)"),"") -> Differs (67% of B2C) | R102: No buying rate. The 70% rule can derive one at import from the selling price. Draft B2B is unapproved. | S102: Not set | T102: Exempt | U102: Not confirmed: CRM basis is empty; draft gives a GST rate, not whether prices include it | V102: Not given | W102: Active, quotable | X102: Category notes only (visit). No service-specific notes. | Y102: Y | Z102: Y | AB102: Unit, No B2B, GST basis, Knowledge, Meaning differs | AC102: 1 | AD102: 1 | AE102: 1 | AF102: 1 | AG102: 0 | AH102: 0 | AI102: 1
...

Sheet Unresolved inputs
A1: Exact inputs still needed
A3: # | B3: Input | C3: Why it blocks | D3: Owner | E3: Where it is entered
A4: 1 | B4: The approved final service and price list (B2C), as a file | C4: Without it no row can be reconciled against an approved value, and nothing can be submitted. The only file in the repo is a planning draft generated by scripts/generate_excel_matrix.mjs with "baseline" prices. | D4: Hinduja management / SecondMedic ops | E4: Settings > Rate card > Import rates
A5: 2 | B5: Read access to the live CareDesk database (Supabase ref eilshdpbnhcohroujaui) or a supervisor export of Settings > Rate card | C5: The connected Supabase account cannot see this project ("You do not have permission"). Any imports or approvals made in the app since the migrations are not visible here. | D5: SecondMedic platform admin | E5: Supabase connector, or Rate card export
A6: 3 | B6: GST basis for the B2C column and for the B2B column (incl_gst / excl_gst / no_gst) | C6: The importer never assumes it; margins are withheld when bases differ or are unset. The draft gives rates (Exempt, 12%, 18%), not whether prices include GST. | D6: SecondMedic finance | E6: Import rates: GST basis selectors
A7: 4 | B7: Effective date for the import | C7: No source has one. Back-dated rates only warn; booked lines keep their snapshot cost. | D7: SecondMedic ops | E7: Import rates: effective date
A8: 5 | B8: Unit decisions (see Unit decisions sheet): 24 h vs shift, 12 hours vs shift, test vs unit, pack sizes, monthly rental | C8: The importer refuses unit mismatches and never converts. Open question already listed in docs/RATES-AND-MARGINS.md. | D8: SecondMedic ops with BMM | E8: Before the import file is built
A9: 6 | B9: Approved provider-specific buying rates, if any differ from 70% | C9: 94 of 95 draft B2B values are not 70% of B2C. Without approval they cannot be used; leaving B2B blank lets the 70% rule apply. | D9: SecondMedic commercial | E9: Rate card > Buying rates, or B2B column
A10: 7 | B10: Decision on generic vs specific codes (BED-HOSP, NURS-HOME, PHYSIO-HOME, ELDER-CARE, OXY-CONC, OXY-CYL, VENT-HOME vs BIPAP-AUTO, XR-HOME vs XR-CHEST / XR-LIMB) | C10: Keeping both gives agents two prices for one need. | D10: Hinduja management | E10: Rate card (deactivate) after decision
A11: 8 | B11: Approval evidence for the 15 prices already on the rate card | C11: They were written by migrations with an automatic approved_at and no approver. Confirm on the live Approvals page or by written Hinduja confirmation. | D11: Hinduja management | E11: Approvals history
A12: 9 | B12: Approved service-specific product notes (summary, questions, inclusions, exclusions, preparation, FAQs) | C12: None exist. Clinical content cannot be written from nothing. | D12: Hinduja clinical + BMM / SecondMedic service owners | E12: Product knowledge > Import
A13: 10 | B13: Named approver and date for scripts S-01 to S-09 and the 12 category notes | C13: Scripts were marked approved by migration (approved_by empty); the category notes migration says "Hinduja to review". | D13: Hinduja management / clinical | E13: Templates approval
A14: 11 | B14: Agent roster and the operations owner for training sign-off | C14: Needed to fill the attendance and competency record. | D14: SecondMedic ops | E14: Training workbook

Sheet Unit decisions
A1: Unit decisions needed before import
A2: Yellow cells are for the business owner. Nothing here is converted automatically.
A4: Code | B4: CRM unit | C4: Draft unit | D4: Question | E4: Decision | F4: Decided by | G4: Date
A5: FEED-SYR-60 | B5: unit | C5: box | D5: Pack size differs: rate card sells one syringe ("unit"), draft sells a pack of 5 ("box"). Different product; never convert.
A6: ECG-12 | B6: unit | C6: test | D6: Rate card "unit" vs draft "test". The importer refuses the row until one wording is chosen.
A7: ECG-RPT | C7: test | D7: New item uses "test"; existing ecg services use "unit". Align the wording before import.
A8: ATTEND-24H | C8: shift | D8: 24-hour cover labelled "shift", the same unit as the 12-hour services. Needs its own unit (e.g. "24 hours") before import.
A9: LAB-ABG | C9: test | D9: New item uses "test"; existing lab services use "unit". Align the wording before import.
A10: LAB-B12 | C10: test | D10: New item uses "test"; existing lab services use "unit". Align the wording before import.
A11: LAB-BLOODC | C11: test | D11: New item uses "test"; existing lab services use "unit". Align the wording before import.
A12: LAB-CBC | B12: unit | C12: test | D12: Rate card "unit" vs draft "test". The importer refuses the row until one wording is chosen.
A13: LAB-CRP | C13: test | D13: New item uses "test"; existing lab services use "unit". Align the wording before import.
A14: LAB-DDIMER | C14: test | D14: New item uses "test"; existing lab services use "unit". Align the wording before import.
A15: LAB-ELECT | C15: test | D15: New item uses "test"; existing lab services use "unit". Align the wording before import.
A16: LAB-HBA1C | B16: unit | C16: test | D16: Rate card "unit" vs draft "test". The importer refuses the row until one wording is chosen.
A17: LAB-ICUPAN | C17: test | D17: New item uses "test"; existing lab services use "unit". Align the wording before import.
A18: LAB-KFT | B18: unit | C18: test | D18: Rate card "unit" vs draft "test". The importer refuses the row until one wording is chosen.
A19: LAB-LFT | B19: unit | C19: test | D19: Rate card "unit" vs draft "test". The importer refuses the row until one wording is chosen.
A20: LAB-LIPID | B20: unit | C20: test | D20: Rate card "unit" vs draft "test". The importer refuses the row until one wording is chosen.
A21: LAB-PANEL | B21: unit | C21: test | D21: Rate card "unit" vs draft "test". The importer refuses the row until one wording is chosen.
A22: LAB-PROCAL | C22: test | D22: New item uses "test"; existing lab services use "unit". Align the wording before import.
A23: LAB-PTINR | C23: test | D23: New item uses "test"; existing lab services use "unit". Align the wording before import.
A24: LAB-THY | B24: unit | C24: test | D24: Rate card "unit" vs draft "test". The importer refuses the row until one wording is chosen.
A25: LAB-URINE | C25: test | D25: New item uses "test"; existing lab services use "unit". Align the wording before import.
A26: LAB-URINEC | C26: test | D26: New item uses "test"; existing lab services use "unit". Align the wording before import.
A27: LAB-VITD | C27: test | D27: New item uses "test"; existing lab services use "unit". Align the wording before import.
A28: NURSE-24H | C28: shift | D28: 24-hour cover labelled "shift", the same unit as the 12-hour services. Needs its own unit (e.g. "24 hours") before import.
A29: NURSE-ICU24 | C29: shift | D29: 24-hour cover labelled "shift", the same unit as the 12-hour services. Needs its own unit (e.g. "24 hours") before import.
A30: VISIT-STD | B30: unit | C30: visit | D30: Rate card "unit" vs draft "visit". The importer refuses the row until one wording is chosen.
A31: VISIT-URG | B31: unit | C31: visit | D31: Rate card "unit" vs draft "visit". The importer refuses the row until one wording is chosen.
A32: XR-ADDITIONAL | B32: 1 Additional X-ray Shoot | D32: Free-text unit "1 Additional X-ray Shoot". Confirm the intended unit wording; buying rates are stored against this exact text.
A33: XR-CHEST | B33: unit | C33: test | D33: Rate card "unit" vs draft "test". The importer refuses the row until one wording is chosen.
A34: XR-HOME | B34: First Shot | D34: Free-text unit "First Shot". Confirm the intended unit wording; buying rates are stored against this exact text.
A35: XR-LIMB | B35: unit | C35: test | D35: Rate card "unit" vs draft "test". The importer refuses the row until one wording is chosen.
A36: XR-PELV | C36: test | D36: New item uses "test"; existing xray services use "unit". Align the wording before import.
A37: XR-PRINT | B37: additional X-ray Print | D37: Free-text unit "additional X-ray Print". Confirm the intended unit wording; buying rates are stored against this exact text.
A38: XR-SPINE | C38: test | D38: New item uses "test"; existing xray services use "unit". Align the wording before import.
A39: ALL RENTALS | B39: day | C39: day | D39: Is a monthly rental tariff needed for beds and equipment? If yes, it is a separate unit ("month") with its own approved price, never 30 x the day rate.
A40: NURSING / ATTENDANT | B40: shift | C40: shift | D40: Do "12 hours" and "24 hours" replace or sit beside the existing shift services (open question in docs/RATES-AND-MARGINS.md)?

Sheet Draft values to confirm
A1: Draft values for business confirmation (not approved, not for import as they stand)
A2: Source: docs/HHCS_CRM_Feature_Matrix_and_Catalogue.xlsx, sheet "85 Services Catalogue", generated by scripts/generate_excel_matrix.mjs (commit 8f6b2b1). Use this only if the business confirms it is the price list; otherwise replace with the approved file.
A5: Code | B5: Name | C5: Category | D5: Unit | E5: Draft B2C (Rs) | F5: Draft B2B (Rs) | G5: Draft GST | H5: On CRM | I5: Confirmed B2C (Rs) | J5: Keep draft B2B or use 70%? | K5: Approver | L5: Date
A6: BED-FOWL | B6: Full Fowler 2-Function Hospital Bed (Rental) | C6: beds | D6: day | E6: 240 | F6: 160 | G6: 18% GST | H6: N
A7: BED-ICU | B7: Motorized ICU Bed (3/5 Function with Remote) | C7: beds | D7: day | E7: 450 | F7: 300 | G7: 18% GST | H7: Y
A8: BED-SEMI | B8: Semi-Fowler Hospital Bed with Railings (Rental) | C8: beds | D8: day | E8: 180 | F8: 120 | G8: 18% GST | H8: N
A9: TYNA-BED | B9: Tubular High-Risk Pressure Redistribution Bed | C9: beds | D9: day | E9: 150 | F9: 100 | G9: 18% GST | H9: Y
A10: ADULT-DIAP | B10: Adult Diapers Tape-Style (Pack of 10 Large) | C10: consumables | D10: box | E10: 550 | F10: 360 | G10: 12% GST | H10: N
A11: BIPAP-MASK | B11: Full-Face Non-Vented BiPAP Cushion Mask | C11: consumables | D11: unit | E11: 2800 | F11: 1800 | G11: 12% GST | H11: N
A12: CAVILON-SP | B12: 3M Cavilon No-Sting Barrier Film Spray (28ml) | C12: consumables | D12: unit | E12: 1100 | F12: 750 | G12: 12% GST | H12: Y
A13: FEED-SYR-60 | B13: Catheter-Tip Feeding Syringes (60ml, Pack of 5) | C13: consumables | D13: box | E13: 280 | F13: 170 | G13: 12% GST | H13: Y
A14: FOLEY-CATH | B14: Silicone Foley Balloon Catheter (All Sizes) | C14: consumables | D14: unit | E14: 320 | F14: 190 | G14: 12% GST | H14: N
A15: GLOVES-BOX | B15: Examination Gloves Box (Powder-Free, 100 pcs) | C15: consumables | D15: box | E15: 450 | F15: 280 | G15: 12% GST | H15: Y
A16: GLOVES-STER | B16: Surgical Sterile Gloves Pairs (Pack of 10) | C16: consumables | D16: box | E16: 350 | F16: 220 | G16: 12% GST | H16: N
A17: HFNC-KIT | B17: Optiflow Nasal Interface & Heated Breathing Tube | C17: consumables | D17: unit | E17: 4500 | F17: 3100 | G17: 12% GST | H17: N
... A100: XR-SPINE | B100: Portable X-Ray: Spine (Cervical / Lumbar) | C100: xray | D100: test | E100: 2600 | F100: 1600 | G100: Exempt | H100: N

Sheet Knowledge coverage
A1: Product knowledge coverage
A3: Target | B3: Summary | C3: Who needs it | D3: Ask the caller | E3: Includes | F3: Excludes | G3: Preparation | H3: FAQ | I3: Status
A4: Category: beds | B4: Yes | C4: Yes | D4: Yes | E4: Yes | F4: Yes | G4: Yes | H4: Yes | I4: Seeded by migration 20261016110000 with the note "no clinical advice; Hinduja to review". Awaiting Hinduja review.
A5: Category: consumables | B5: Yes | C5: Yes | D5: Yes | E5: Yes | F5: Yes | G5: Yes | H5: Yes | I5: Seeded by migration 20261016110000 with the note "no clinical advice; Hinduja to review". Awaiting Hinduja review.
A6: Category: ecg | B6: Yes | C6: Yes | D6: Yes | E6: Yes | F6: Yes | G6: Yes | H6: Yes | I6: Seeded by migration 20261016110000 with the note "no clinical advice; Hinduja to review". Awaiting Hinduja review.
A7: Category: eldercare | B7: Yes | C7: Yes | D7: Yes | E7: Yes | F7: Yes | G7: Yes | H7: Yes | I7: Seeded by migration 20261016110000 with the note "no clinical advice; Hinduja to review". Awaiting Hinduja review.
A8: Category: equipment | B8: Yes | C8: Yes | D8: Yes | E8: Yes | F8: Yes | G8: Yes | H8: Yes | I8: Seeded by migration 20261016110000 with the note "no clinical advice; Hinduja to review". Awaiting Hinduja review.
A9: Category: homecare | B9: Yes | C9: Yes | D9: Yes | E9: Yes | F9: Yes | G9: Yes | H9: Yes | I9: Seeded by migration 20261016110000 with the note "no clinical advice; Hinduja to review". Awaiting Hinduja review.
A10: Category: icu | B10: Yes | C10: Yes | D10: Yes | E10: Yes | F10: Yes | G10: Yes | H10: Yes | I10: Seeded by migration 20261016110000 with the note "no clinical advice; Hinduja to review". Awaiting Hinduja review.
A11: Category: lab | B11: Yes | C11: Yes | D11: Yes | E11: Yes | F11: Yes | G11: Yes | H11: Yes | I11: Seeded by migration 20261016110000 with the note "no clinical advice; Hinduja to review". Awaiting Hinduja review.
A12: Category: nursing | B12: Yes | C12: Yes | D12: Yes | E12: Yes | F12: Yes | G12: Yes | H12: Yes | I12: Seeded by migration 20261016110000 with the note "no clinical advice; Hinduja to review". Awaiting Hinduja review.
A13: Category: physio | B13: Yes | C13: Yes | D13: Yes | E13: Yes | F13: Yes | G13: Yes | H13: Yes | I13: Seeded by migration 20261016110000 with the note "no clinical advice; Hinduja to review". Awaiting Hinduja review.
A14: Category: visit | B14: Yes | C14: Yes | D14: Yes | E14: Yes | F14: Yes | G14: Yes | H14: Yes | I14: Seeded by migration 20261016110000 with the note "no clinical advice; Hinduja to review". Awaiting Hinduja review.
... A18: Category "other" | B18: No | C18: No | D18: No | E18: No | F18: No | G18: No | H18: No | I18: No default; no service uses it today, but the 70% import routes "other" (e.g. ambulance) to BMM, so a new service there would show "No product knowledge yet".

Sheet Scripts review
A1: Call scripts reviewed against dispositions and the rate card
A3: Code | B3: Title | C3: Stage | D3: Ends with | E3: Finding | F3: Proposed change | G3: Needs approval from
A4: S-01 | B4: Inbound greeting & consent | C4: Opening | D4: Intake disposition | E4: Consent step and S-09 hand-off are sound. Step 7 promises a quote on WhatsApp "shortly", but 25 BMM services are not priced and are quoted after assessment. | F4: Step 7: "You will receive the quote on WhatsApp. For nursing, equipment and beds the quote follows the home assessment." | G4: Hinduja management
A5: S-02 | B5: Home Assessment & Pricing Explanation | C5: Opening / pricing | D5: Assessment booked | E5: Hard-codes "Hinduja Home Care" where S-01 uses {{brand}}. States the nurse is "Hinduja-certified": a claim to confirm. | F5: Use {{brand}}; confirm or remove "Hinduja-certified". | G5: Hinduja management
A6: S-03 | B6: Callback opening (missed call) | C6: Opening / follow-up | D6: Callback outcome | E6: Step 3 says close as "Not reached". That outcome does not exist: outcomes are Resolved, Follow-up needed, Wrong number, No longer needed, and a connected call is never unreachable (migration 20261015180000). | F6: Step 3: "If wrong person: apologise, confirm the number and close the callback with the outcome Wrong number." | G6: Hinduja management
A7: S-04 | B7: Discharge home-care requirement capture | C7: Requirement capture | D7: Intake disposition (step 8) | E7: Matches the intake form and the 8 dispositions. Mentions 24 h needs, but no 24 h service is on the rate card. | F7: None until the unit decision on 24 h is made. | G7: n/a
A8: S-05 | B8: Diagnostics at home (tests, X-ray, ECG) | C8: Requirement capture / pricing | D8: Intake disposition | E8: Tells agents to read the price from the Product knowledge panel. XR-HOME (Rs 2,000 first shot) and XR-CHEST (Rs 2,200) both fit "chest X-ray at home": two prices. | F8: After the overlap decision, name the code to quote for each X-ray request. | G8: Hinduja management
A9: S-06 | B9: Price and budget conversation | C9: Pricing | D9: Discount approval if any | E9: Offers "12 h instead of 24 h" and "semi-Fowler instead of motorised bed". None of these are priced in the CRM (24 h and semi-Fowler do not exist; BED-ICU is Rs 0). | F9: Keep; usable only after the price list is approved and imported. | G9: n/a
A10: S-07 | B10: Closing and next steps | C10: Closure | D10: Disposition | E10: Sound. | F10: None. | G10: n/a
A11: S-09 | B11: Emergency at home | C11: Escalation | D11: Emergency escalation | E11: Clinical safety content. | F11: None; record Hinduja clinical sign-off. | G11: Hinduja clinical
A12: (none) | B12: Quote follow-up | C12: Follow-up | D12: Follow-up requested / callback outcome | E12: No script covers calling back a family who received a quote or asked for time (disposition "Follow-up requested", callback outcome "Follow-up needed"). S-08 is unused. | F12: Proposed S-08 draft text is on the "Proposed S-08" sheet. Not loaded. | G12: Hinduja management
A14: Approval evidence: every script row is status "approved" with approved_at set by migration and approved_by empty. No named approver or date is recorded.
A15: Dispositions: the Knowledge page guide (src/pages/Knowledge.jsx) lists the same 8 intake values as the database check (requirement_captured ... duplicate). Callback outcomes are a separate list of 4.

Sheet Proposed S-08
A1: Proposed S-08: Quote follow-up (draft, awaiting approval, not loaded)
A3: Good {{greeting_time}}, this is {{agent_name}} from {{brand}}, calling about the quote for {{patient_name}}, reference {{case_no}}. Is this a good time?
A4: 1. If not a good time: agree a time and log it as Follow-up needed.
A5: 2. Ask whether the family has gone through the quote and has questions. Answer only from the quote and the Product knowledge panel.
A6: 3. If price is the concern, follow S-06. Never promise a discount.
A7: 4. If they want to go ahead: confirm the agreed list with the decision maker and the start date, then follow S-07.
A8: 5. If they have arranged care elsewhere or no longer need it: thank them and close with the matching outcome (No longer needed) and reason.
A9: 6. Set the disposition or callback outcome before closing the case screen.

Sheet Awaiting approval
A1: Content awaiting business or clinical approval
A3: Item | B3: Count | C3: Approver | D3: Status
A4: Final B2C price list (whole catalogue) | B4: 1 file | C4: Hinduja management (in-app rate_import approval) | D4: Not received
A5: Services on the rate card at Rs 0 | B5: =Totals!C13 -> 25 | C5: Hinduja management | D5: Not priced
A6: Prices already on the rate card without a recorded approver | B6: =Totals!C5-Totals!C13 -> 15 | C6: Hinduja management | D6: Confirm on live Approvals
A7: Provider exceptions to the 70% buying rule | B7: =Totals!D16 -> 94 | C7: SecondMedic commercial | D7: None approved
A8: Generic vs specific code overlaps | B8: =Totals!C10 -> 12 | C8: Hinduja management | D8: Decision needed
A9: Unit decisions | B9: =COUNTA('Unit decisions'!A5:A100) -> 36 | C9: SecondMedic ops with BMM | D9: Decision needed
A10: Category knowledge notes | B10: 12 | C10: Hinduja clinical (lab, X-ray, ECG, ICU, nursing); Hinduja management (includes / excludes) | D10: Seeded, "Hinduja to review"
A11: Service-specific knowledge notes | B11: 0 | C11: Hinduja clinical + service owners | D11: Not written
A12: Call scripts with no named approver | B12: 8 | C12: Hinduja management; S-09 Hinduja clinical | D12: Marked approved by migration only
A13: Script corrections (S-01, S-02, S-03, S-05) and new S-08 | B13: 5 | C13: Hinduja management | D13: Proposed
A14: Hinduja management access to margins | B14: 1 decision | C14: SecondMedic + Hinduja | D14: Open (docs/RATES-AND-MARGINS.md)

Sheet Verification evidence
A1: Verification evidence (16 Oct 2026, repo HEAD 36f2df2)
A3: Check | B3: How | C3: Result
A4: Live database access | B4: Supabase connector: execute_sql on project eilshdpbnhcohroujaui | C4: Refused: "You do not have permission to perform this action". The connected account lists only secondmedic-crm and staff-portal.
A5: Catalogue end state | B5: All 44 migrations applied in order to an in-memory PGlite database; services, providers, provider_rates, service_price_history, rate_imports, service_knowledge, templates read | C5: 40 services (15 priced, 25 at Rs 0), 0 buying rates, 0 imports, tax_basis empty on all, 12 category notes, 0 service notes, 9 scripts.
A6: Rates, import, margins, cost confidentiality (SQL, per role) | B6: npx vitest run test/rates.test.mjs test/product-knowledge.test.mjs test/provider-fulfilment.test.mjs | C6: Passed (3 files). Covers: agent, coordinator, client_manager, client_clinical, field staff, medical desk, provider and admin refused case_margins / margin_report; 0 provider_rates rows visible to agent, field, client, clinical, medical, provider; no buying rate in audit_log, timeline, patient quote text or Hinduja MIS pack; administrator sees margins.
A7: Same rules through the Worker API | B7: npm run rehearse (includes rates.itest.mjs) | C7: Passed: 357 API checks. Covers 403 on rate import, margin report, provider_rates / rate_imports / case_item_costs reads, direct writes, margins inside an agent batch; case lines read by an agent contain no buy / margin fields.
A8: BMM partner API (bmm_leads) | B8: Read migration 20261015170200_bmm_release_scope.sql | C8: Returns service code, name, category, quantity, unit only. case_item_costs is joined for routing (provider_id), no rate or amount is emitted. Not covered by a test.
A9: Partner Excel export (Leads page) | B9: Read src/pages/Leads.jsx download() | C9: Columns: case, provider, patient, services, hospital, discharge, status, visit, note. No money. Not covered by a test.
A10: Hinduja rate approval payload | B10: Read submit_rate_import in 20261015140000_rate_import_derived_buying.sql | C10: Carries selling prices, tax basis, dates and the file name only. The file name is shown to Hinduja: name import files without "buying" or provider rates.
A11: Quotation PDF | B11: Read src/lib/pdf.js columns | C11: Unit, qty, rate (selling), total. No cost fields.
A12: Product knowledge shows Rs 0 | B12: Read src/components/ProductKnowledge.jsx and src/pages/Knowledge.jsx | C12: Defect: unpriced services render "Rs 0.00 / day" to agents (Console picker correctly says "quote required"). Patch proposed: product-knowledge-unpriced.patch (lint passes and both files parse; the full vite build could not run here because the xlsx package host cdn.sheetjs.com is blocked from this workspace, so run npm run build before shipping).
A13: Repo unchanged | B13: git status after all runs | C13: Clean. Nothing committed, pushed, imported or activated.
